Workbook

Sheet Cover
B2: PLS GROUP LIMITED
B3: ASX: PLS | Spodumene concentrate | Pilgangoora, Western Australia
B5: Equity valuation model
B6: FMAA x Shared Value Project - Investing for the Future Case Competition 2026
B8: Prepared for | C8: FMAA Asset Management - Australian ASX 200 long-only fund
B9: Coverage team | C9: Shared Value Coverage
B10: Valuation date | C10: 5 September 2026
B11: Reporting currency | C11: A$ (Australian dollars), millions unless stated
B12: Fiscal year end | C12: 30 June
B14: HOW TO USE THIS MODEL
B15: 1. Assumptions!C7 holds the scenario switch. Change it to Bear / Base / Bull and the entire
B16: model - production, prices, costs, capex, statements, DCF and target price - repoints.
B17: 2. Every projected cell is a live formula. Nothing downstream of Assumptions is typed in.
B18: 3. Blue text = hardcoded input. Black = formula. Green = link to another sheet.
B19: Yellow fill = key judgement the reviewer should interrogate first.
B20: 4. Sources lists the provenance of every input, tagged A (actual) / G (guidance) /
B21: M (market) / D (derived) / E (our estimate) / C (prescribed by the case).
B23: CONTENTS
B24: Assumptions | C24: Scenario switch, market data, CAPM and WACC build, operating drivers
B25: Deck | C25: Production by asset, realised price, unit cost and capex - all three scenarios
B26: Revenue Build | C26: Volume x price bridge by asset, royalties, freight
B27: Income Statement | C27: FY24A-FY36F P&L
B28: Balance Sheet | C28: FY24A-FY36F balance sheet
B29: Cash Flow | C29: FY24A-FY36F cash flow and net working capital
B30: DCF | C30: Unlevered FCFF, WACC discounting, terminal value, equity bridge
B31: Sensitivity | C31: WACC x TGR, price x cost, price x volume data tables
B32: Scenario Summary | C32: Bear / Base / Bull outputs side by side and probability weighting
B33: SOTP NAV | C33: Risked asset-by-asset net asset value cross-check
B34: Trading Comps | C34: ASX diversified peers and global lithium pure-plays
B35: Precedents | C35: Lithium M&A precedent transaction multiples
... B40: Sources | C40: Provenance register for every input
B42: IMPORTANT
B43: Prepared as a university case-competition submission using publicly available information.
B44: Not investment advice and not a substitute for independent professional research.
B45: Forecasts are the authors' estimates and will differ from outcomes.

Sheet Assumptions
B2: Assumptions and WACC
B3: Every driver in the model resolves to a cell on this sheet | S3: Bear
B4: PLS Group Limited (ASX: PLS) | Valuation date 5 September 2026 | All figures A$ unless stated | S4: Base
S5: Bull
B6: SCENARIO SWITCH
B7: Active scenario | C7: Base | F7: Change this cell to repoint the whole model. Bear / Base / Bull.
B8: Scenario index | C8: =MATCH($C$7,$S$3:$S$5,0) -> 2 | F8: 1 = Bear, 2 = Base, 3 = Bull. Drives every CHOOSE() in the model.
B10: MARKET DATA
B11: Last close (A$/share) | C11: 5.48 | D11: M Market Index / Google Finance, early Sep-26
B12: Shares on issue (m) | C12: 3220 | D12: M stockanalysis.com
B13: Market capitalisation (A$m) | C13: =C11*C12 -> 17645.6
B14: 52-week high (A$) | C14: 6.81
B15: 52-week low (A$) | C15: 1.91
B16: Move off 52-week low | C16: =C11/C15-1 -> 1.8691099 | D16: The central objection this pitch must answer
B18: CAPITAL STRUCTURE
B19: Cash and equivalents, FY26A (A$m) | C19: 2290 | D19: A FY26 result, 24-Aug-26
B20: Borrowings, FY26A (A$m) | C20: 828 | D20: E US$600m senior notes translated at spot - VERIFY
B21: Net cash / (net debt) (A$m) | C21: =C19-C20 -> 1462
B22: Enterprise value (A$m) | C22: =C13-C21 -> 16183.6
B23: Target gearing D/(D+E) | C23: 0.1 | D23: E through-cycle target; PLS is currently net cash
B25: COST OF CAPITAL (CAPM inputs prescribed by the case)
B26: Risk-free rate | C26: 0.05 | D26: C FMAA case p.6 - prescribed
B27: Market risk premium | C27: 0.06 | D27: C FMAA case p.6 - prescribed
B28: Equity beta | C28: 0.73 | D28: C FMAA case p.6 - Yahoo 5Y monthly
B29: Cost of equity = Rf + B x MRP | C29: =C26+C28*C27 -> 0.0938
B30: Pre-tax cost of debt | C30: 0.0625 | D30: E indicative senior note coupon - VERIFY
B31: Corporate tax rate | C31: 0.3 | D31: Australian statutory rate
B32: After-tax cost of debt | C32: =C30*(1-C31) -> 0.04375
B33: WACC | C33: =(1-C23)*C29+C23*C32 -> 0.088795
B35: TERMINAL VALUE
B36: Terminal growth rate (scenario-driven) | C36: =CHOOSE($C$8,0.015,0.025,0.03) -> 0.025 | D36: E below long-run Australian nominal GDP growth
B37: Terminal FCFF basis | C37: Final forecast year FCFF grown at TGR
B39: OPERATING DRIVERS
B40: Corporate and admin cost (A$m p.a., FY27 base) | C40: 95 | D40: E
B41: Cost inflation p.a. | C41: 0.025 | D41: E
B42: WA State royalty (% of realised revenue) | C42: 0.05 | D42: WA ad valorem royalty on concentrate - VERIFY rate and basis
B43: D&A as % of prior-year capex (steady state) | C43: 0.85 | D43: E
B44: Net working capital as % of revenue | C44: 0.08 | D44: E
B46: OREBODY AND MINE LIFE (drives the terminal value)
B47: Mineral Resource (Mt) | C47: 446 | D47: A 446Mt at 1.28% Li2O, June-2025 update
B48: Ore Reserve (Mt) | C48: 214.2 | D48: A Aug-2023 statement - not restated since the 2025 resource upgrade
B49: Assumed resource-to-reserve conversion | C49: 0.75 | D49: E KEY JUDGEMENT: the reserve alone does not support the modelled expansion
B50: Mineable ore base (Mt) | C50: =C47*C49 -> 334.5
B51: Reserve grade (% Li2O) | C51: 0.0119 | D51: A 1.19% Li2O
B52: Lithia recovery | C52: 0.765 | D52: A ~76.5% reported for FY26
B53: Concentrate grade (% Li2O) | C53: 0.052 | D53: A PLS ships ~SC5.2
B54: Mass pull (t concentrate per t ore) | C54: =C51*C52/C53 -> 0.17506731
B55: Cap on terminal life (years) | C55: 25 | D55: E beyond 25 years the discounted contribution is negligible
B57: BENCHMARK AND MANDATE (from the case)
B58: S&P/ASX 200 return, FY26 | C58: 0.059 | D58: C FMAA case p.4
B59: Fund return, FY25 | C59: 0.079 | D59: C FMAA case p.4 - index +2.0%
B60: Required outperformance | C60: =C59-C58 -> 0.02
B62: Tags: A = reported actual | G = company guidance | M = market data | D = derived | E = our estimate | C = prescribed by the case

Sheet Deck
B2: Operating deck
B3: Three scenarios held side by side; the ACTIVE block is what the model reads
B4: PLS Group Limited (ASX: PLS) | Valuation date 5 September 2026 | All figures A$ unless stated
B6: Spodumene concentrate production (kt) | C6: FY24A | D6: FY25A | E6: FY26A | F6: FY27F | G6: FY28F | H6: FY29F | I6: FY30F | J6: FY31F | K6: FY32F | L6: FY33F | M6: FY34F | N6: FY35F | O6: FY36F
B7: Bear case
B8: Pilgangoora (Pilgan plant) | F8: 880 | G8: 880 | H8: 870 | I8: 870 | J8: 860 | K8: 860 | L8: 850 | M8: 850 | N8: 850 | O8: 850
B9: Ngungaju plant | F9: 150 | G9: 170 | H9: 160 | I9: 120 | J9: 120 | K9: 140 | L9: 150 | M9: 160 | N9: 170 | O9: 170
B10: P2000 expansion | F10: 0 | G10: 0 | H10: 0 | I10: 0 | J10: 0 | K10: 0 | L10: 0 | M10: 0 | N10: 0 | O10: 0
B11: Colina, Brazil | F11: 0 | G11: 0 | H11: 0 | I11: 0 | J11: 0 | K11: 0 | L11: 0 | M11: 0 | N11: 0 | O11: 0
B12: Total - Bear | F12: =SUM(F8:F11) -> 1030 | G12: =SUM(G8:G11) -> 1050 | H12: =SUM(H8:H11) -> 1030 | I12: =SUM(I8:I11) -> 990 | J12: =SUM(J8:J11) -> 980 | K12: =SUM(K8:K11) -> 1000 | L12: =SUM(L8:L11) -> 1000 | M12: =SUM(M8:M11) -> 1010 | ... O12: =SUM(O8:O11) -> 1020
B14: Base case
B15: Pilgangoora (Pilgan plant) | F15: 900 | G15: 920 | H15: 920 | I15: 920 | J15: 920 | K15: 920 | L15: 920 | M15: 920 | N15: 920 | O15: 920
B16: Ngungaju plant | F16: 165 | G16: 195 | H16: 195 | I16: 195 | J16: 195 | K16: 195 | L16: 195 | M16: 195 | N16: 195 | O16: 195
B17: P2000 expansion | F17: 0 | G17: 0 | H17: 0 | I17: 250 | J17: 550 | K17: 800 | L17: 885 | M17: 885 | N17: 885 | O17: 885
B18: Colina, Brazil | F18: 0 | G18: 0 | H18: 0 | I18: 0 | J18: 0 | K18: 150 | L18: 350 | M18: 460 | N18: 500 | O18: 500
B19: Total - Base | F19: =SUM(F15:F18) -> 1065 | G19: =SUM(G15:G18) -> 1115 | H19: =SUM(H15:H18) -> 1115 | I19: =SUM(I15:I18) -> 1365 | J19: =SUM(J15:J18) -> 1665 | K19: =SUM(K15:K18) -> 2065 | L19: =SUM(L15:L18) -> 2350 | M19: =SUM(M15:M18) -> 2460 | ... O19: =SUM(O15:O18) -> 2500
B21: Bull case
B22: Pilgangoora (Pilgan plant) | F22: 920 | G22: 960 | H22: 970 | I22: 970 | J22: 970 | K22: 970 | L22: 970 | M22: 970 | N22: 970 | O22: 970
B23: Ngungaju plant | F23: 180 | G23: 205 | H23: 205 | I23: 205 | J23: 205 | K23: 205 | L23: 205 | M23: 205 | N23: 205 | O23: 205
B24: P2000 expansion | F24: 0 | G24: 0 | H24: 120 | I24: 450 | J24: 780 | K24: 925 | L24: 950 | M24: 950 | N24: 950 | O24: 950
B25: Colina, Brazil | F25: 0 | G25: 0 | H25: 0 | I25: 0 | J25: 180 | K25: 380 | L25: 500 | M25: 560 | N25: 560 | O25: 560
B26: Total - Bull | F26: =SUM(F22:F25) -> 1100 | G26: =SUM(G22:G25) -> 1165 | H26: =SUM(H22:H25) -> 1295 | I26: =SUM(I22:I25) -> 1625 | J26: =SUM(J22:J25) -> 2135 | K26: =SUM(K22:K25) -> 2480 | L26: =SUM(L22:L25) -> 2625 | M26: =SUM(M22:M25) -> 2685 | ... O26: =SUM(O22:O25) -> 2685
B28: ACTIVE (driven by Assumptions!C7)
B29: Pilgangoora (Pilgan plant) | F29: =CHOOSE(Assumptions!$C$8,F8,F15,F22) -> 900 | G29: =CHOOSE(Assumptions!$C$8,G8,G15,G22) -> 920 | H29: =CHOOSE(Assumptions!$C$8,H8,H15,H22) -> 920 | I29: =CHOOSE(Assumptions!$C$8,I8,I15,I22) -> 920 | J29: =CHOOSE(Assumptions!$C$8,J8,J15,J22) -> 920 | K29: =CHOOSE(Assumptions!$C$8,K8,K15,K22) -> 920 | L29: =CHOOSE(Assumptions!$C$8,L8,L15,L22) -> 920 | M29: =CHOOSE(Assumptions!$C$8,M8,M15,M22) -> 920 | ... O29: =CHOOSE(Assumptions!$C$8,O8,O15,O22) -> 920
B30: Ngungaju plant | F30: =CHOOSE(Assumptions!$C$8,F9,F16,F23) -> 165 | G30: =CHOOSE(Assumptions!$C$8,G9,G16,G23) -> 195 | H30: =CHOOSE(Assumptions!$C$8,H9,H16,H23) -> 195 | I30: =CHOOSE(Assumptions!$C$8,I9,I16,I23) -> 195 | J30: =CHOOSE(Assumptions!$C$8,J9,J16,J23) -> 195 | K30: =CHOOSE(Assumptions!$C$8,K9,K16,K23) -> 195 | L30: =CHOOSE(Assumptions!$C$8,L9,L16,L23) -> 195 | M30: =CHOOSE(Assumptions!$C$8,M9,M16,M23) -> 195 | ... O30: =CHOOSE(Assumptions!$C$8,O9,O16,O23) -> 195
B31: P2000 expansion | F31: =CHOOSE(Assumptions!$C$8,F10,F17,F24) -> 0 | G31: =CHOOSE(Assumptions!$C$8,G10,G17,G24) -> 0 | H31: =CHOOSE(Assumptions!$C$8,H10,H17,H24) -> 0 | I31: =CHOOSE(Assumptions!$C$8,I10,I17,I24) -> 250 | J31: =CHOOSE(Assumptions!$C$8,J10,J17,J24) -> 550 | K31: =CHOOSE(Assumptions!$C$8,K10,K17,K24) -> 800 | L31: =CHOOSE(Assumptions!$C$8,L10,L17,L24) -> 885 | M31: =CHOOSE(Assumptions!$C$8,M10,M17,M24) -> 885 | ... O31: =CHOOSE(Assumptions!$C$8,O10,O17,O24) -> 885
B32: Colina, Brazil | F32: =CHOOSE(Assumptions!$C$8,F11,F18,F25) -> 0 | G32: =CHOOSE(Assumptions!$C$8,G11,G18,G25) -> 0 | H32: =CHOOSE(Assumptions!$C$8,H11,H18,H25) -> 0 | I32: =CHOOSE(Assumptions!$C$8,I11,I18,I25) -> 0 | J32: =CHOOSE(Assumptions!$C$8,J11,J18,J25) -> 0 | K32: =CHOOSE(Assumptions!$C$8,K11,K18,K25) -> 150 | L32: =CHOOSE(Assumptions!$C$8,L11,L18,L25) -> 350 | M32: =CHOOSE(Assumptions!$C$8,M11,M18,M25) -> 460 | ... O32: =CHOOSE(Assumptions!$C$8,O11,O18,O25) -> 500
B33: Total production (kt) | C33: 725.3 | D33: 755.6 | E33: 879.5 | F33: =SUM(F29:F32) -> 1065 | G33: =SUM(G29:G32) -> 1115 | H33: =SUM(H29:H32) -> 1115 | I33: =SUM(I29:I32) -> 1365 | J33: =SUM(J29:J32) -> 1665 | K33: =SUM(K29:K32) -> 2065 | L33: =SUM(L29:L32) -> 2350 | M33: =SUM(M29:M32) -> 2460 | ... O33: =SUM(O29:O32) -> 2500
B34: Concentrate sold (kt) | C34: 707 | D34: 749 | E34: 891.6 | F34: =F33 -> 1065 | G34: =G33 -> 1115 | H34: =H33 -> 1115 | I34: =I33 -> 1365 | J34: =J33 -> 1665 | K34: =K33 -> 2065 | L34: =L33 -> 2350 | M34: =M33 -> 2460 | ... O34: =O33 -> 2500 | Q34: Forecast assumes sales = production (no inventory build)
B35: Growth in production | D35: =D33/C33-1 -> 0.041775817 | E35: =E33/D33-1 -> 0.16397565 | F35: =F33/E33-1 -> 0.21091529 | G35: =G33/F33-1 -> 0.046948357 | H35: =H33/G33-1 -> 0 | I35: =I33/H33-1 -> 0.22421525 | J35: =J33/I33-1 -> 0.21978022 | K35: =K33/J33-1 -> 0.24024024 | ... O35: =O33/N33-1 -> 0
B37: Realised price (US$/dmt of concentrate) | C37: FY24A | D37: FY25A | E37: FY26A | F37: FY27F | G37: FY28F | H37: FY29F | I37: FY30F | J37: FY31F | K37: FY32F | L37: FY33F | M37: FY34F | N37: FY35F | O37: FY36F
B38: Bear case | F38: 1350 | G38: 1150 | H38: 1050 | I38: 1050 | J38: 1150 | K38: 1250 | L38: 1350 | M38: 1450 | N38: 1500 | O38: 1550
B39: Base case | F39: 1700 | G39: 1780 | H39: 1850 | I39: 1800 | J39: 1750 | K39: 1750 | L39: 1750 | M39: 1750 | N39: 1750 | O39: 1750
B40: Bull case | F40: 2050 | G40: 2400 | H40: 2600 | I40: 2450 | J40: 2300 | K40: 2150 | L40: 2050 | M40: 1975 | N40: 1925 | O40: 1900
B41: ACTIVE realised price (US$/t) | C41: 1116 | D41: 688 | E41: 1488 | F41: =CHOOSE(Assumptions!$C$8,F38,F39,F40) -> 1700 | G41: =CHOOSE(Assumptions!$C$8,G38,G39,G40) -> 1780 | H41: =CHOOSE(Assumptions!$C$8,H38,H39,H40) -> 1850 | I41: =CHOOSE(Assumptions!$C$8,I38,I39,I40) -> 1800 | J41: =CHOOSE(Assumptions!$C$8,J38,J39,J40) -> 1750 | K41: =CHOOSE(Assumptions!$C$8,K38,K39,K40) -> 1750 | L41: =CHOOSE(Assumptions!$C$8,L38,L39,L40) -> 1750 | M41: =CHOOSE(Assumptions!$C$8,M38,M39,M40) -> 1750 | ... O41: =CHOOSE(Assumptions!$C$8,O38,O39,O40) -> 1750
B42: AUD/USD | C42: 0.657 | D42: 0.646 | E42: 0.65 | F42: 0.66 | G42: 0.67 | H42: 0.68 | I42: 0.69 | J42: 0.7 | K42: 0.7 | L42: 0.7 | M42: 0.7 | N42: 0.7 | O42: 0.7
B43: Realised price (A$/t) | C43: =C41/C42 -> 1698.6301 | D43: =D41/D42 -> 1065.0155 | E43: =E41/E42 -> 2289.2308 | F43: =F41/F42 -> 2575.7576 | G43: =G41/G42 -> 2656.7164 | H43: =H41/H42 -> 2720.5882 | I43: =I41/I42 -> 2608.6957 | J43: =J41/J42 -> 2500 | ... O43: =O41/O42 -> 2500
B45: Unit operating cost, FOB (A$/dmt) | C45: FY24A | D45: FY25A | E45: FY26A | F45: FY27F | G45: FY28F | H45: FY29F | I45: FY30F | J45: FY31F | K45: FY32F | L45: FY33F | M45: FY34F | N45: FY35F | O45: FY36F
B46: Bear case | F46: 625 | G46: 645 | H46: 655 | I46: 640 | J46: 625 | K46: 615 | L46: 610 | M46: 610 | N46: 610 | O46: 610
B47: Base case | F47: 600 | G47: 590 | H47: 585 | I47: 580 | J47: 570 | K47: 565 | L47: 565 | M47: 565 | N47: 565 | O47: 565
B48: Bull case | F48: 585 | G48: 565 | H48: 550 | I48: 540 | J48: 530 | K48: 525 | L48: 520 | M48: 520 | N48: 520 | O48: 520
B49: ACTIVE unit cost (A$/t FOB) | C49: 655 | D49: 627 | E49: 569 | F49: =CHOOSE(Assumptions!$C$8,F46,F47,F48) -> 600 | G49: =CHOOSE(Assumptions!$C$8,G46,G47,G48) -> 590 | H49: =CHOOSE(Assumptions!$C$8,H46,H47,H48) -> 585 | I49: =CHOOSE(Assumptions!$C$8,I46,I47,I48) -> 580 | J49: =CHOOSE(Assumptions!$C$8,J46,J47,J48) -> 570 | K49: =CHOOSE(Assumptions!$C$8,K46,K47,K48) -> 565 | L49: =CHOOSE(Assumptions!$C$8,L46,L47,L48) -> 565 | M49: =CHOOSE(Assumptions!$C$8,M46,M47,M48) -> 565 | ... O49: =CHOOSE(Assumptions!$C$8,O46,O47,O48) -> 565
B50: Unit cash margin (A$/t) | C50: =C43-C49 -> 1043.6301 | D50: =D43-D49 -> 438.01548 | E50: =E43-E49 -> 1720.2308 | F50: =F43-F49 -> 1975.7576 | G50: =G43-G49 -> 2066.7164 | H50: =H43-H49 -> 2135.5882 | I50: =I43-I49 -> 2028.6957 | J50: =J43-J49 -> 1930 | ... O50: =O43-O49 -> 1935
B51: Unit cash margin (%) | C51: =IFERROR(C50/C43,0) -> 0.61439516 | D51: =IFERROR(D50/D43,0) -> 0.41127616 | E51: =IFERROR(E50/E43,0) -> 0.75144489 | F51: =IFERROR(F50/F43,0) -> 0.76705882 | G51: =IFERROR(G50/G43,0) -> 0.77792135 | H51: =IFERROR(H50/H43,0) -> 0.78497297 | I51: =IFERROR(I50/I43,0) -> 0.77766667 | J51: =IFERROR(J50/J43,0) -> 0.772 | ... O51: =IFERROR(O50/O43,0) -> 0.774
B53: Capital expenditure (A$m) | C53: FY24A | D53: FY25A | E53: FY26A | F53: FY27F | G53: FY28F | H53: FY29F | I53: FY30F | J53: FY31F | K53: FY32F | L53: FY33F | M53: FY34F | N53: FY35F | O53: FY36F
B54: Bear case | F54: 620 | G54: 400 | H54: 340 | I54: 320 | J54: 300 | K54: 295 | L54: 290 | M54: 290 | N54: 290 | O54: 290
B55: Base case | F55: 652 | G55: 880 | H55: 1020 | I55: 760 | J55: 560 | K55: 520 | L55: 430 | M55: 390 | N55: 370 | O55: 370
B56: Bull case | F56: 685 | G56: 1020 | H56: 1130 | I56: 900 | J56: 720 | K56: 600 | L56: 480 | M56: 430 | N56: 410 | O56: 410
B57: ACTIVE capex (A$m) | C57: 820 | D57: 500 | E57: 328 | F57: =CHOOSE(Assumptions!$C$8,F54,F55,F56) -> 652 | G57: =CHOOSE(Assumptions!$C$8,G54,G55,G56) -> 880 | H57: =CHOOSE(Assumptions!$C$8,H54,H55,H56) -> 1020 | I57: =CHOOSE(Assumptions!$C$8,I54,I55,I56) -> 760 | J57: =CHOOSE(Assumptions!$C$8,J54,J55,J56) -> 560 | K57: =CHOOSE(Assumptions!$C$8,K54,K55,K56) -> 520 | L57: =CHOOSE(Assumptions!$C$8,L54,L55,L56) -> 430 | M57: =CHOOSE(Assumptions!$C$8,M54,M55,M56) -> 390 | ... O57: =CHOOSE(Assumptions!$C$8,O54,O55,O56) -> 370
B59: FY27 ACTIVE production 1,065kt and capex A$652m sit at the midpoints of company guidance of 1,030-1,100kt and A$620-685m.
B60: Realised price is below the SC6 benchmark because PLS ships a lower-grade concentrate on an FOB basis. FY26A realised US$1,488/t against an SC6 CIF China benchmark near US$2,200/t.

Sheet Revenue Build
B2: Revenue build
B3: Volume x realised price by asset, reconciled to reported revenue
B4: PLS Group Limited (ASX: PLS) | Valuation date 5 September 2026 | All figures A$ unless stated
B6: Volumes by asset (kt) | C6: FY24A | D6: FY25A | E6: FY26A | F6: FY27F | G6: FY28F | H6: FY29F | I6: FY30F | J6: FY31F | K6: FY32F | L6: FY33F | M6: FY34F | N6: FY35F | O6: FY36F
B7: Pilgangoora (Pilgan plant) | F7: =Deck!F29 -> 900 | G7: =Deck!G29 -> 920 | H7: =Deck!H29 -> 920 | I7: =Deck!I29 -> 920 | J7: =Deck!J29 -> 920 | K7: =Deck!K29 -> 920 | L7: =Deck!L29 -> 920 | M7: =Deck!M29 -> 920 | ... O7: =Deck!O29 -> 920
B8: Ngungaju plant | F8: =Deck!F30 -> 165 | G8: =Deck!G30 -> 195 | H8: =Deck!H30 -> 195 | I8: =Deck!I30 -> 195 | J8: =Deck!J30 -> 195 | K8: =Deck!K30 -> 195 | L8: =Deck!L30 -> 195 | M8: =Deck!M30 -> 195 | ... O8: =Deck!O30 -> 195
B9: P2000 expansion | F9: =Deck!F31 -> 0 | G9: =Deck!G31 -> 0 | H9: =Deck!H31 -> 0 | I9: =Deck!I31 -> 250 | J9: =Deck!J31 -> 550 | K9: =Deck!K31 -> 800 | L9: =Deck!L31 -> 885 | M9: =Deck!M31 -> 885 | ... O9: =Deck!O31 -> 885
B10: Colina, Brazil | F10: =Deck!F32 -> 0 | G10: =Deck!G32 -> 0 | H10: =Deck!H32 -> 0 | I10: =Deck!I32 -> 0 | J10: =Deck!J32 -> 0 | K10: =Deck!K32 -> 150 | L10: =Deck!L32 -> 350 | M10: =Deck!M32 -> 460 | ... O10: =Deck!O32 -> 500
B11: Total concentrate sold (kt) | C11: =Deck!C34 -> 707 | D11: =Deck!D34 -> 749 | E11: =Deck!E34 -> 891.6 | F11: =Deck!F34 -> 1065 | G11: =Deck!G34 -> 1115 | H11: =Deck!H34 -> 1115 | I11: =Deck!I34 -> 1365 | J11: =Deck!J34 -> 1665 | ... O11: =Deck!O34 -> 2500
B13: Price realisation | C13: FY24A | D13: FY25A | E13: FY26A | F13: FY27F | G13: FY28F | H13: FY29F | I13: FY30F | J13: FY31F | K13: FY32F | L13: FY33F | M13: FY34F | N13: FY35F | O13: FY36F
B14: Realised price (US$/t) | C14: =Deck!C41 -> 1116 | D14: =Deck!D41 -> 688 | E14: =Deck!E41 -> 1488 | F14: =Deck!F41 -> 1700 | G14: =Deck!G41 -> 1780 | H14: =Deck!H41 -> 1850 | I14: =Deck!I41 -> 1800 | J14: =Deck!J41 -> 1750 | ... O14: =Deck!O41 -> 1750
B15: AUD/USD | C15: =Deck!C42 -> 0.657 | D15: =Deck!D42 -> 0.646 | E15: =Deck!E42 -> 0.65 | F15: =Deck!F42 -> 0.66 | G15: =Deck!G42 -> 0.67 | H15: =Deck!H42 -> 0.68 | I15: =Deck!I42 -> 0.69 | J15: =Deck!J42 -> 0.7 | ... O15: =Deck!O42 -> 0.7
B16: Realised price (A$/t) | C16: =C14/C15 -> 1698.6301 | D16: =D14/D15 -> 1065.0155 | E16: =E14/E15 -> 2289.2308 | F16: =F14/F15 -> 2575.7576 | G16: =G14/G15 -> 2656.7164 | H16: =H14/H15 -> 2720.5882 | I16: =I14/I15 -> 2608.6957 | J16: =J14/J15 -> 2500 | ... O16: =O14/O15 -> 2500
B18: Revenue (A$m) | C18: FY24A | D18: FY25A | E18: FY26A | F18: FY27F | G18: FY28F | H18: FY29F | I18: FY30F | J18: FY31F | K18: FY32F | L18: FY33F | M18: FY34F | N18: FY35F | O18: FY36F
B19: Gross concentrate revenue | C19: =C11*C16/1000 -> 1200.9315 | D19: =D11*D16/1000 -> 797.69659 | E19: =E11*E16/1000 -> 2041.0782 | F19: =F11*F16/1000 -> 2743.1818 | G19: =G11*G16/1000 -> 2962.2388 | H19: =H11*H16/1000 -> 3033.4559 | I19: =I11*I16/1000 -> 3560.8696 | J19: =J11*J16/1000 -> 4162.5 | ... O19: =O11*O16/1000 -> 6250
B20: Freight, moisture and timing adjustment (% of gross) | C20: 0 | D20: 0.036 | E20: 0.0525 | F20: 0.054 | G20: 0.054 | H20: 0.054 | I20: 0.054 | J20: 0.054 | K20: 0.054 | L20: 0.054 | M20: 0.054 | N20: 0.054 | O20: 0.054 | Q20: Calibrated to reported revenue in FY25A and FY26A; held flat at 5.4% across the forecast
B21: Revenue | C21: =C19*(1-C20) -> 1200.9315 | D21: =D19*(1-D20) -> 768.97952 | E21: =E19*(1-E20) -> 1933.9216 | F21: =F19*(1-F20) -> 2595.05 | G21: =G19*(1-G20) -> 2802.2779 | H21: =H19*(1-H20) -> 2869.6493 | I21: =I19*(1-I20) -> 3368.5826 | J21: =J19*(1-J20) -> 3937.725 | ... O21: =O19*(1-O20) -> 5912.5
B22: Memo: reported revenue (A$m) | C22: 1254 | D22: 769 | E22: 1934
B23: Variance to reported | C23: =IFERROR(C21/C22-1,"") -> -0.042319373 | D23: =IFERROR(D21/D22-1,"") -> -2.6635855e-05 | E23: =IFERROR(E21/E22-1,"") -> -4.0563201e-05
B25: The realisation adjustment captures freight to the customer's port, moisture and grade adjustments, and the timing lag between the reference price and shipment.

Sheet Income Statement
B2: Income statement
B3: FY24A-FY36F, A$m
B4: PLS Group Limited (ASX: PLS) | Valuation date 5 September 2026 | All figures A$ unless stated
B6: A$m | C6: FY24A | D6: FY25A | E6: FY26A | F6: FY27F | G6: FY28F | H6: FY29F | I6: FY30F | J6: FY31F | K6: FY32F | L6: FY33F | M6: FY34F | N6: FY35F | O6: FY36F
B7: Revenue | C7: ='Revenue Build'!C21 -> 1200.9315 | D7: ='Revenue Build'!D21 -> 768.97952 | E7: ='Revenue Build'!E21 -> 1933.9216 | F7: ='Revenue Build'!F21 -> 2595.05 | G7: ='Revenue Build'!G21 -> 2802.2779 | H7: ='Revenue Build'!H21 -> 2869.6493 | I7: ='Revenue Build'!I21 -> 3368.5826 | J7: ='Revenue Build'!J21 -> 3937.725 | ... O7: ='Revenue Build'!O21 -> 5912.5
B8: Operating costs (FOB) | C8: =-Deck!C34*Deck!C49/1000 -> -463.085 | D8: =-Deck!D34*Deck!D49/1000 -> -469.623 | E8: =-Deck!E34*Deck!E49/1000 -> -507.3204 | F8: =-Deck!F34*Deck!F49/1000 -> -639 | G8: =-Deck!G34*Deck!G49/1000 -> -657.85 | H8: =-Deck!H34*Deck!H49/1000 -> -652.275 | I8: =-Deck!I34*Deck!I49/1000 -> -791.7 | J8: =-Deck!J34*Deck!J49/1000 -> -949.05 | ... O8: =-Deck!O34*Deck!O49/1000 -> -1412.5
B9: State royalties | C9: =-C7*Assumptions!$C$42 -> -60.046575 | D9: =-D7*Assumptions!$C$42 -> -38.448976 | E9: =-E7*Assumptions!$C$42 -> -96.696078 | F9: =-F7*Assumptions!$C$42 -> -129.7525 | G9: =-G7*Assumptions!$C$42 -> -140.1139 | H9: =-H7*Assumptions!$C$42 -> -143.48246 | I9: =-I7*Assumptions!$C$42 -> -168.42913 | J9: =-J7*Assumptions!$C$42 -> -196.88625 | ... O9: =-O7*Assumptions!$C$42 -> -295.625
B10: Corporate, administration and cost-definition reconciliation | C10: =C27-C7-C8-C9 -> -139.79993 | D10: =D27-D7-D8-D9 -> -163.90754 | E10: =E27-E7-E8-E9 -> -192.90507 | F10: =-Assumptions!$C$40*(1+Assumptions!$C$41)^(0) -> -95 | G10: =-Assumptions!$C$40*(1+Assumptions!$C$41)^(1) -> -97.375 | H10: =-Assumptions!$C$40*(1+Assumptions!$C$41)^(2) -> -99.809375 | I10: =-Assumptions!$C$40*(1+Assumptions!$C$41)^(3) -> -102.30461 | J10: =-Assumptions!$C$40*(1+Assumptions!$C$41)^(4) -> -104.86222 | K10: =-Assumptions!$C$40*(1+Assumptions!$C$41)^(5) -> -107.48378 | L10: =-Assumptions!$C$40*(1+Assumptions!$C$41)^(6) -> -110.17087 | M10: =-Assumptions!$C$40*(1+Assumptions!$C$41)^(7) -> -112.92515 | N10: =-Assumptions!$C$40*(1+Assumptions!$C$41)^(8) -> -115.74828 | O10: =-Assumptions!$C$40*(1+Assumptions!$C$41)^(9) -> -118.64198 | Q10: Historical columns absorb the difference between this simplified cost build and reported underlying EBITDA, so FY24A-FY26A tie exactly.
B11: EBITDA | C11: =SUM(C7:C10) -> 538 | D11: =SUM(D7:D10) -> 97 | E11: =SUM(E7:E10) -> 1137 | F11: =SUM(F7:F10) -> 1731.2975 | G11: =SUM(G7:G10) -> 1906.939 | H11: =SUM(H7:H10) -> 1974.0824 | I11: =SUM(I7:I10) -> 2306.1489 | J11: =SUM(J7:J10) -> 2686.9265 | ... O11: =SUM(O7:O10) -> 4085.733
B12: EBITDA margin | C12: =IFERROR(C11/C7,0) -> 0.44798558 | D12: =IFERROR(D11/D7,0) -> 0.1261412 | E12: =IFERROR(E11/E7,0) -> 0.58792457 | F12: =IFERROR(F11/F7,0) -> 0.66715381 | G12: =IFERROR(G11/G7,0) -> 0.68049604 | H12: =IFERROR(H11/H7,0) -> 0.68791767 | I12: =IFERROR(I11/I7,0) -> 0.68460511 | J12: =IFERROR(J11/J7,0) -> 0.68235505 | ... O12: =IFERROR(O11/O7,0) -> 0.69103307
B13: Depreciation and amortisation | C13: -300 | D13: -330 | E13: -360 | F13: =-'Balance Sheet'!F25 -> -368 | G13: =-'Balance Sheet'!G25 -> -400.66 | H13: =-'Balance Sheet'!H25 -> -455.7841 | I13: =-'Balance Sheet'!I25 -> -520.66893 | J13: =-'Balance Sheet'!J25 -> -548.192 | K13: =-'Balance Sheet'!K25 -> -549.54992 | L13: =-'Balance Sheet'!L25 -> -546.15168 | M13: =-'Balance Sheet'!M25 -> -532.79424 | ... O13: =-'Balance Sheet'!O25 -> -499.54002
B14: EBIT | C14: =C11+C13 -> 238 | D14: =D11+D13 -> -233 | E14: =E11+E13 -> 777 | F14: =F11+F13 -> 1363.2975 | G14: =G11+G13 -> 1506.279 | H14: =H11+H13 -> 1518.2983 | I14: =I11+I13 -> 1785.4799 | J14: =J11+J13 -> 2138.7345 | ... O14: =O11+O13 -> 3586.193
B15: Net interest income / (expense) | C15: -10 | D15: 25 | E15: 40 | F15: ='Balance Sheet'!F26 -> 39.85 | G15: ='Balance Sheet'!G26 -> 53.87608 | H15: ='Balance Sheet'!H26 -> 64.618391 | I15: ='Balance Sheet'!I26 -> 72.859334 | J15: ='Balance Sheet'!J26 -> 87.706254 | K15: ='Balance Sheet'!K26 -> 116.58285 | L15: ='Balance Sheet'!L26 -> 155.79073 | M15: ='Balance Sheet'!M26 -> 206.60204 | ... O15: ='Balance Sheet'!O26 -> 322.50245
B16: Profit before tax | C16: =C14+C15 -> 228 | D16: =D14+D15 -> -208 | E16: =E14+E15 -> 817 | F16: =F14+F15 -> 1403.1475 | G16: =G14+G15 -> 1560.1551 | H16: =H14+H15 -> 1582.9167 | I16: =I14+I15 -> 1858.3393 | J16: =J14+J15 -> 2226.4408 | ... O16: =O14+O15 -> 3908.6955
B17: Income tax expense | C17: =-MAX(0,C16)*Assumptions!$C$31 -> -68.4 | D17: =-MAX(0,D16)*Assumptions!$C$31 -> 0 | E17: =-MAX(0,E16)*Assumptions!$C$31 -> -245.1 | F17: =-MAX(0,F16)*Assumptions!$C$31 -> -420.94425 | G17: =-MAX(0,G16)*Assumptions!$C$31 -> -468.04653 | H17: =-MAX(0,H16)*Assumptions!$C$31 -> -474.87502 | I17: =-MAX(0,I16)*Assumptions!$C$31 -> -557.50178 | J17: =-MAX(0,J16)*Assumptions!$C$31 -> -667.93223 | ... O17: =-MAX(0,O16)*Assumptions!$C$31 -> -1172.6086
B18: NPAT | C18: =C16+C17 -> 159.6 | D18: =D16+D17 -> -208 | E18: =E16+E17 -> 571.9 | F18: =F16+F17 -> 982.20325 | G18: =G16+G17 -> 1092.1086 | H18: =H16+H17 -> 1108.0417 | I18: =I16+I17 -> 1300.8375 | J18: =J16+J17 -> 1558.5085 | ... O18: =O16+O17 -> 2736.0868
B20: Per share and returns | C20: FY24A | D20: FY25A | E20: FY26A | F20: FY27F | G20: FY28F | H20: FY29F | I20: FY30F | J20: FY31F | K20: FY32F | L20: FY33F | M20: FY34F | N20: FY35F | O20: FY36F
B21: EPS (A$) | C21: =C18/Assumptions!$C$12 -> 0.049565217 | D21: =D18/Assumptions!$C$12 -> -0.064596273 | E21: =E18/Assumptions!$C$12 -> 0.1776087 | F21: =F18/Assumptions!$C$12 -> 0.30503207 | G21: =G18/Assumptions!$C$12 -> 0.33916415 | H21: =H18/Assumptions!$C$12 -> 0.34411233 | I21: =I18/Assumptions!$C$12 -> 0.4039868 | J21: =J18/Assumptions!$C$12 -> 0.48400886 | ... O21: =O18/Assumptions!$C$12 -> 0.8497164
B22: Dividend payout ratio | F22: 0.3 | G22: 0.3 | H22: 0.3 | I22: 0.5 | J22: 0.5 | K22: 0.5 | L22: 0.5 | M22: 0.5 | N22: 0.5 | O22: 0.5 | Q22: Policy is 20-30% of free cash flow; we step up to 50% from FY30 once the P2000 build is funded
B23: DPS (A$) | F23: =MAX(0,F21)*F22 -> 0.09150962 | G23: =MAX(0,G21)*G22 -> 0.10174925 | H23: =MAX(0,H21)*H22 -> 0.1032337 | I23: =MAX(0,I21)*I22 -> 0.2019934 | J23: =MAX(0,J21)*J22 -> 0.24200443 | K23: =MAX(0,K21)*K22 -> 0.3187351 | L23: =MAX(0,L21)*L22 -> 0.37517181 | M23: =MAX(0,M21)*M22 -> 0.40195518 | ... O23: =MAX(0,O21)*O22 -> 0.4248582
B24: Total dividends (A$m) | F24: =F23*Assumptions!$C$12 -> 294.66098 | G24: =G23*Assumptions!$C$12 -> 327.63257 | H24: =H23*Assumptions!$C$12 -> 332.41251 | I24: =I23*Assumptions!$C$12 -> 650.41875 | J24: =J23*Assumptions!$C$12 -> 779.25427 | K24: =K23*Assumptions!$C$12 -> 1026.327 | L24: =L23*Assumptions!$C$12 -> 1208.0532 | M24: =M23*Assumptions!$C$12 -> 1294.2957 | ... O24: =O23*Assumptions!$C$12 -> 1368.0434
B25: Dividend yield on last close | F25: =F23/Assumptions!$C$11 -> 0.016698836 | G25: =G23/Assumptions!$C$11 -> 0.018567381 | H25: =H23/Assumptions!$C$11 -> 0.018838266 | I25: =I23/Assumptions!$C$11 -> 0.036860109 | J25: =J23/Assumptions!$C$11 -> 0.044161393 | K25: =K23/Assumptions!$C$11 -> 0.058163339 | L25: =L23/Assumptions!$C$11 -> 0.06846201 | M25: =M23/Assumptions!$C$11 -> 0.073349485 | ... O25: =O23/Assumptions!$C$11 -> 0.077528869
B27: Memo: reported underlying EBITDA (A$m) | C27: 538 | D27: 97 | E27: 1137
B28: Memo: reported NPAT (A$m) | C28: 257.8 | D28: -196 | E28: 526

Sheet Balance Sheet
B2: Balance sheet
B3: FY26A opening position rolled forward to FY36F, A$m
B4: PLS Group Limited (ASX: PLS) | Valuation date 5 September 2026 | All figures A$ unless stated
B6: A$m | C6: FY24A | D6: FY25A | E6: FY26A | F6: FY27F | G6: FY28F | H6: FY29F | I6: FY30F | J6: FY31F | K6: FY32F | L6: FY33F | M6: FY34F | N6: FY35F | O6: FY36F
B7: Drivers
B8: D&A rate on opening PP&E | F8: 0.115 | G8: 0.115 | H8: 0.115 | I8: 0.115 | J8: 0.115 | K8: 0.115 | L8: 0.115 | M8: 0.115 | N8: 0.115 | O8: 0.115 | Q8: E approximates an 8-9 year average remaining asset life
B9: Interest earned on opening cash | F9: 0.04 | G9: 0.04 | H9: 0.04 | I9: 0.04 | J9: 0.04 | K9: 0.04 | L9: 0.04 | M9: 0.04 | N9: 0.04 | O9: 0.04 | Q9: E
B10: Interest paid on opening debt | F10: =Assumptions!$C$29*0+0.0625 -> 0.0625 | G10: =Assumptions!$C$29*0+0.0625 -> 0.0625 | H10: =Assumptions!$C$29*0+0.0625 -> 0.0625 | I10: =Assumptions!$C$29*0+0.0625 -> 0.0625 | J10: =Assumptions!$C$29*0+0.0625 -> 0.0625 | K10: =Assumptions!$C$29*0+0.0625 -> 0.0625 | L10: =Assumptions!$C$29*0+0.0625 -> 0.0625 | M10: =Assumptions!$C$29*0+0.0625 -> 0.0625 | ... O10: =Assumptions!$C$29*0+0.0625 -> 0.0625
B12: Assets
B13: Cash and cash equivalents | E13: =Assumptions!$C$19 -> 2290 | F13: ='Cash Flow'!F23 -> 2640.652 | G13: ='Cash Flow'!G23 -> 2909.2098 | H13: ='Cash Flow'!H23 -> 3115.2333 | I13: ='Cash Flow'!I23 -> 3486.4064 | J13: ='Cash Flow'!J23 -> 4208.3212 | K13: ='Cash Flow'!K23 -> 5188.5182 | L13: ='Cash Flow'!L23 -> 6458.8011 | M13: ='Cash Flow'!M23 -> 7875.079 | ... O13: ='Cash Flow'!O23 -> 10853.895
B14: Net working capital | E14: ='Income Statement'!E7*Assumptions!$C$44 -> 154.71372 | F14: ='Income Statement'!F7*Assumptions!$C$44 -> 207.604 | G14: ='Income Statement'!G7*Assumptions!$C$44 -> 224.18223 | H14: ='Income Statement'!H7*Assumptions!$C$44 -> 229.57194 | I14: ='Income Statement'!I7*Assumptions!$C$44 -> 269.48661 | J14: ='Income Statement'!J7*Assumptions!$C$44 -> 315.018 | K14: ='Income Statement'!K7*Assumptions!$C$44 -> 390.698 | L14: ='Income Statement'!L7*Assumptions!$C$44 -> 444.62 | ... O14: ='Income Statement'!O7*Assumptions!$C$44 -> 473
B15: Property, plant and equipment (net) | E15: 3200 | F15: =E15+Deck!F57-F25 -> 3484 | G15: =F15+Deck!G57-G25 -> 3963.34 | H15: =G15+Deck!H57-H25 -> 4527.5559 | I15: =H15+Deck!I57-I25 -> 4766.887 | J15: =I15+Deck!J57-J25 -> 4778.695 | K15: =J15+Deck!K57-K25 -> 4749.145 | L15: =K15+Deck!L57-L25 -> 4632.9934 | M15: =L15+Deck!M57-M25 -> 4490.1991 | ... O15: =N15+Deck!O57-O25 -> 4214.2862 | Q15: E FY26A net book value - VERIFY against the annual report
B16: Total assets | E16: =SUM(E13:E15) -> 5644.7137 | F16: =SUM(F13:F15) -> 6332.256 | G16: =SUM(G13:G15) -> 7096.732 | H16: =SUM(H13:H15) -> 7872.3612 | I16: =SUM(I13:I15) -> 8522.7799 | J16: =SUM(J13:J15) -> 9302.0342 | K16: =SUM(K13:K15) -> 10328.361 | L16: =SUM(L13:L15) -> 11536.414 | ... O16: =SUM(O13:O15) -> 15541.181
B18: Liabilities and equity
B19: Borrowings | E19: =Assumptions!$C$20 -> 828 | F19: =E19+'Cash Flow'!F20 -> 828 | G19: =F19+'Cash Flow'!G20 -> 828 | H19: =G19+'Cash Flow'!H20 -> 828 | I19: =H19+'Cash Flow'!I20 -> 828 | J19: =I19+'Cash Flow'!J20 -> 828 | K19: =J19+'Cash Flow'!K20 -> 828 | L19: =K19+'Cash Flow'!L20 -> 828 | M19: =L19+'Cash Flow'!M20 -> 828 | ... O19: =N19+'Cash Flow'!O20 -> 828
B20: Shareholders' equity | E20: =E16-E19 -> 4816.7137 | F20: =E20+'Income Statement'!F18-'Income Statement'!F24 -> 5504.256 | G20: =F20+'Income Statement'!G18-'Income Statement'!G24 -> 6268.732 | H20: =G20+'Income Statement'!H18-'Income Statement'!H24 -> 7044.3612 | I20: =H20+'Income Statement'!I18-'Income Statement'!I24 -> 7694.7799 | J20: =I20+'Income Statement'!J18-'Income Statement'!J24 -> 8474.0342 | K20: =J20+'Income Statement'!K18-'Income Statement'!K24 -> 9500.3612 | L20: =K20+'Income Statement'!L18-'Income Statement'!L24 -> 10708.414 | M20: =L20+'Income Statement'!M18-'Income Statement'!M24 -> 12002.71 | ... O20: =N20+'Income Statement'!O18-'Income Statement'!O24 -> 14713.181
B21: Total liabilities and equity | E21: =E19+E20 -> 5644.7137 | F21: =F19+F20 -> 6332.256 | G21: =G19+G20 -> 7096.732 | H21: =H19+H20 -> 7872.3612 | I21: =I19+I20 -> 8522.7799 | J21: =J19+J20 -> 9302.0342 | K21: =K19+K20 -> 10328.361 | L21: =L19+L20 -> 11536.414 | ... O21: =O19+O20 -> 15541.181
B22: Balance check (must be nil) | E22: =E16-E21 -> 0 | F22: =F16-F21 -> 0 | G22: =G16-G21 -> 0 | H22: =H16-H21 -> 0 | I22: =I16-I21 -> 0 | J22: =J16-J21 -> 0 | K22: =K16-K21 -> 0 | L22: =L16-L21 -> 0 | ... O22: =O16-O21 -> 0
B24: Memo
B25: D&A charge | F25: =E15*F8 -> 368 | G25: =F15*G8 -> 400.66 | H25: =G15*H8 -> 455.7841 | I25: =H15*I8 -> 520.66893 | J25: =I15*J8 -> 548.192 | K25: =J15*K8 -> 549.54992 | L25: =K15*L8 -> 546.15168 | M25: =L15*M8 -> 532.79424 | ... O25: =N15*O8 -> 499.54002
B26: Net interest income / (expense) | F26: =E13*F9-E19*F10 -> 39.85 | G26: =F13*G9-F19*G10 -> 53.87608 | H26: =G13*H9-G19*H10 -> 64.618391 | I26: =H13*I9-H19*I10 -> 72.859334 | J26: =I13*J9-I19*J10 -> 87.706254 | K26: =J13*K9-J19*K10 -> 116.58285 | L26: =K13*L9-K19*L10 -> 155.79073 | M26: =L13*M9-L19*M10 -> 206.60204 | ... O26: =N13*O9-N19*O10 -> 322.50245
B27: Net cash / (net debt) | E27: =E13-E19 -> 1462 | F27: =F13-F19 -> 1812.652 | G27: =G13-G19 -> 2081.2098 | H27: =H13-H19 -> 2287.2333 | I27: =I13-I19 -> 2658.4064 | J27: =J13-J19 -> 3380.3212 | K27: =K13-K19 -> 4360.5182 | L27: =L13-L19 -> 5630.8011 | ... O27: =O13-O19 -> 10025.895
B28: Return on equity | F28: =IFERROR('Income Statement'!F18/E20,0) -> 0.20391564 | G28: =IFERROR('Income Statement'!G18/F20,0) -> 0.19841166 | H28: =IFERROR('Income Statement'!H18/G20,0) -> 0.17675691 | I28: =IFERROR('Income Statement'!I18/H20,0) -> 0.18466366 | J28: =IFERROR('Income Statement'!J18/I20,0) -> 0.20254102 | K28: =IFERROR('Income Statement'!K18/J20,0) -> 0.24222867 | L28: =IFERROR('Income Statement'!L18/K20,0) -> 0.25431733 | M28: =IFERROR('Income Statement'!M18/L20,0) -> 0.24173433 | ... O28: =IFERROR('Income Statement'!O18/N20,0) -> 0.205025
B29: Return on invested capital (after tax) | F29: =IFERROR('Income Statement'!F14*(1-Assumptions!$C$31)/(E15+E14),0) -> 0.28446786 | G29: =IFERROR('Income Statement'!G14*(1-Assumptions!$C$31)/(F15+F14),0) -> 0.28561983 | H29: =IFERROR('Income Statement'!H14*(1-Assumptions!$C$31)/(G15+G14),0) -> 0.25380375 | I29: =IFERROR('Income Statement'!I14*(1-Assumptions!$C$31)/(H15+H14),0) -> 0.26272911 | J29: =IFERROR('Income Statement'!J14*(1-Assumptions!$C$31)/(I15+I14),0) -> 0.29726035 | K29: =IFERROR('Income Statement'!K14*(1-Assumptions!$C$31)/(J15+J14),0) -> 0.38695664 | L29: =IFERROR('Income Statement'!L14*(1-Assumptions!$C$31)/(K15+K14),0) -> 0.44885669 | M29: =IFERROR('Income Statement'!M14*(1-Assumptions!$C$31)/(L15+L14),0) -> 0.48132257 | ... O29: =IFERROR('Income Statement'!O14*(1-Assumptions!$C$31)/(N15+N14),0) -> 0.52115957
B31: FY24A and FY25A balance sheets are not modelled; the DCF runs off the FY26A closing position.

Sheet Cash Flow
B2: Cash flow statement
B3: FY26A opening cash rolled forward to FY36F, A$m
B4: PLS Group Limited (ASX: PLS) | Valuation date 5 September 2026 | All figures A$ unless stated
B6: A$m | C6: FY24A | D6: FY25A | E6: FY26A | F6: FY27F | G6: FY28F | H6: FY29F | I6: FY30F | J6: FY31F | K6: FY32F | L6: FY33F | M6: FY34F | N6: FY35F | O6: FY36F
B7: Operating
B8: EBITDA | E8: ='Income Statement'!E11 -> 1137 | F8: ='Income Statement'!F11 -> 1731.2975 | G8: ='Income Statement'!G11 -> 1906.939 | H8: ='Income Statement'!H11 -> 1974.0824 | I8: ='Income Statement'!I11 -> 2306.1489 | J8: ='Income Statement'!J11 -> 2686.9265 | K8: ='Income Statement'!K11 -> 3365.33 | L8: ='Income Statement'!L11 -> 3841.9416 | ... O8: ='Income Statement'!O11 -> 4085.733
B9: Net interest received / (paid) | F9: ='Balance Sheet'!F26 -> 39.85 | G9: ='Balance Sheet'!G26 -> 53.87608 | H9: ='Balance Sheet'!H26 -> 64.618391 | I9: ='Balance Sheet'!I26 -> 72.859334 | J9: ='Balance Sheet'!J26 -> 87.706254 | K9: ='Balance Sheet'!K26 -> 116.58285 | L9: ='Balance Sheet'!L26 -> 155.79073 | M9: ='Balance Sheet'!M26 -> 206.60204 | ... O9: ='Balance Sheet'!O26 -> 322.50245
B10: Tax paid | F10: ='Income Statement'!F17 -> -420.94425 | G10: ='Income Statement'!G17 -> -468.04653 | H10: ='Income Statement'!H17 -> -474.87502 | I10: ='Income Statement'!I17 -> -557.50178 | J10: ='Income Statement'!J17 -> -667.93223 | K10: ='Income Statement'!K17 -> -879.70887 | L10: ='Income Statement'!L17 -> -1035.4742 | M10: ='Income Statement'!M17 -> -1109.3963 | ... O10: ='Income Statement'!O17 -> -1172.6086
B11: Movement in net working capital | F11: =-('Balance Sheet'!F14-'Balance Sheet'!E14) -> -52.890276 | G11: =-('Balance Sheet'!G14-'Balance Sheet'!F14) -> -16.578233 | H11: =-('Balance Sheet'!H14-'Balance Sheet'!G14) -> -5.3897083 | I11: =-('Balance Sheet'!I14-'Balance Sheet'!H14) -> -39.914668 | J11: =-('Balance Sheet'!J14-'Balance Sheet'!I14) -> -45.531391 | K11: =-('Balance Sheet'!K14-'Balance Sheet'!J14) -> -75.68 | L11: =-('Balance Sheet'!L14-'Balance Sheet'!K14) -> -53.922 | M11: =-('Balance Sheet'!M14-'Balance Sheet'!L14) -> -20.812 | ... O11: =-('Balance Sheet'!O14-'Balance Sheet'!N14) -> 0
B12: Operating cash flow | F12: =SUM(F8:F11) -> 1297.313 | G12: =SUM(G8:G11) -> 1476.1903 | H12: =SUM(H8:H11) -> 1558.4361 | I12: =SUM(I8:I11) -> 1781.5918 | J12: =SUM(J8:J11) -> 2061.1692 | K12: =SUM(K8:K11) -> 2526.5239 | L12: =SUM(L8:L11) -> 2908.3362 | M12: =SUM(M8:M11) -> 3100.5736 | ... O12: =SUM(O8:O11) -> 3235.6268
B14: Investing
B15: Capital expenditure | E15: =-Deck!E57 -> -328 | F15: =-Deck!F57 -> -652 | G15: =-Deck!G57 -> -880 | H15: =-Deck!H57 -> -1020 | I15: =-Deck!I57 -> -760 | J15: =-Deck!J57 -> -560 | K15: =-Deck!K57 -> -520 | L15: =-Deck!L57 -> -430 | ... O15: =-Deck!O57 -> -370
B16: Free cash flow to the firm (pre-financing) | F16: =F12+F15 -> 645.31297 | G16: =G12+G15 -> 596.19033 | H16: =H12+H15 -> 538.43609 | I16: =I12+I15 -> 1021.5918 | J16: =J12+J15 -> 1501.1692 | K16: =K12+K15 -> 2006.5239 | L16: =L12+L15 -> 2478.3362 | M16: =M12+M15 -> 2710.5736 | ... O16: =O12+O15 -> 2865.6268
B18: Financing
B19: Dividends paid | F19: =-'Income Statement'!F24 -> -294.66098 | G19: =-'Income Statement'!G24 -> -327.63257 | H19: =-'Income Statement'!H24 -> -332.41251 | I19: =-'Income Statement'!I24 -> -650.41875 | J19: =-'Income Statement'!J24 -> -779.25427 | K19: =-'Income Statement'!K24 -> -1026.327 | L19: =-'Income Statement'!L24 -> -1208.0532 | M19: =-'Income Statement'!M24 -> -1294.2957 | ... O19: =-'Income Statement'!O24 -> -1368.0434
B20: Net debt drawn / (repaid) | F20: 0 | G20: 0 | H20: 0 | I20: 0 | J20: 0 | K20: 0 | L20: 0 | M20: 0 | N20: 0 | O20: 0 | Q20: E base case assumes the US$600m notes are refinanced at maturity
B21: Net movement in cash | F21: =F16+F19+F20 -> 350.652 | G21: =G16+G19+G20 -> 268.55776 | H21: =H16+H19+H20 -> 206.02358 | I21: =I16+I19+I20 -> 371.17301 | J21: =J16+J19+J20 -> 721.91488 | K21: =K16+K19+K20 -> 980.19694 | L21: =L16+L19+L20 -> 1270.2829 | M21: =M16+M19+M20 -> 1416.2779 | ... O21: =O16+O19+O20 -> 1497.5834
B22: Opening cash | F22: ='Balance Sheet'!E13 -> 2290 | G22: ='Balance Sheet'!F13 -> 2640.652 | H22: ='Balance Sheet'!G13 -> 2909.2098 | I22: ='Balance Sheet'!H13 -> 3115.2333 | J22: ='Balance Sheet'!I13 -> 3486.4064 | K22: ='Balance Sheet'!J13 -> 4208.3212 | L22: ='Balance Sheet'!K13 -> 5188.5182 | M22: ='Balance Sheet'!L13 -> 6458.8011 | ... O22: ='Balance Sheet'!N13 -> 9356.3113
B23: Closing cash | F23: =F22+F21 -> 2640.652 | G23: =G22+G21 -> 2909.2098 | H23: =H22+H21 -> 3115.2333 | I23: =I22+I21 -> 3486.4064 | J23: =J22+J21 -> 4208.3212 | K23: =K22+K21 -> 5188.5182 | L23: =L22+L21 -> 6458.8011 | M23: =M22+M21 -> 7875.079 | ... O23: =O22+O21 -> 10853.895
B25: Tax paid is shown equal to the accrued charge; PLS carries franking credits and tax losses that in practice defer cash tax.

Sheet DCF
B2: Discounted cash flow
B3: Unlevered FCFF for the ACTIVE scenario, discounted at WACC on a mid-year convention
B4: PLS Group Limited (ASX: PLS) | Valuation date 5 September 2026 | All figures A$ unless stated
B6: A$m | C6: FY24A | D6: FY25A | E6: FY26A | F6: FY27F | G6: FY28F | H6: FY29F | I6: FY30F | J6: FY31F | K6: FY32F | L6: FY33F | M6: FY34F | N6: FY35F | O6: FY36F
B7: EBIT | F7: ='Income Statement'!F14 -> 1363.2975 | G7: ='Income Statement'!G14 -> 1506.279 | H7: ='Income Statement'!H14 -> 1518.2983 | I7: ='Income Statement'!I14 -> 1785.4799 | J7: ='Income Statement'!J14 -> 2138.7345 | K7: ='Income Statement'!K14 -> 2815.78 | L7: ='Income Statement'!L14 -> 3295.7899 | M7: ='Income Statement'!M14 -> 3491.3856 | ... O7: ='Income Statement'!O14 -> 3586.193
B8: Less: tax on EBIT | F8: =-MAX(0,F7)*Assumptions!$C$31 -> -408.98925 | G8: =-MAX(0,G7)*Assumptions!$C$31 -> -451.8837 | H8: =-MAX(0,H7)*Assumptions!$C$31 -> -455.4895 | I8: =-MAX(0,I7)*Assumptions!$C$31 -> -535.64398 | J8: =-MAX(0,J7)*Assumptions!$C$31 -> -641.62036 | K8: =-MAX(0,K7)*Assumptions!$C$31 -> -844.73401 | L8: =-MAX(0,L7)*Assumptions!$C$31 -> -988.73698 | M8: =-MAX(0,M7)*Assumptions!$C$31 -> -1047.4157 | ... O8: =-MAX(0,O7)*Assumptions!$C$31 -> -1075.8579
B9: NOPAT | F9: =F7+F8 -> 954.30825 | G9: =G7+G8 -> 1054.3953 | H9: =H7+H8 -> 1062.8088 | I9: =I7+I8 -> 1249.836 | J9: =J7+J8 -> 1497.1142 | K9: =K7+K8 -> 1971.046 | L9: =L7+L8 -> 2307.053 | M9: =M7+M8 -> 2443.9699 | ... O9: =O7+O8 -> 2510.3351
B10: Add back: D&A | F10: ='Balance Sheet'!F25 -> 368 | G10: ='Balance Sheet'!G25 -> 400.66 | H10: ='Balance Sheet'!H25 -> 455.7841 | I10: ='Balance Sheet'!I25 -> 520.66893 | J10: ='Balance Sheet'!J25 -> 548.192 | K10: ='Balance Sheet'!K25 -> 549.54992 | L10: ='Balance Sheet'!L25 -> 546.15168 | M10: ='Balance Sheet'!M25 -> 532.79424 | ... O10: ='Balance Sheet'!O25 -> 499.54002
B11: Less: capital expenditure | F11: =-Deck!F57 -> -652 | G11: =-Deck!G57 -> -880 | H11: =-Deck!H57 -> -1020 | I11: =-Deck!I57 -> -760 | J11: =-Deck!J57 -> -560 | K11: =-Deck!K57 -> -520 | L11: =-Deck!L57 -> -430 | M11: =-Deck!M57 -> -390 | ... O11: =-Deck!O57 -> -370
B12: Less: increase in net working capital | F12: ='Cash Flow'!F11 -> -52.890276 | G12: ='Cash Flow'!G11 -> -16.578233 | H12: ='Cash Flow'!H11 -> -5.3897083 | I12: ='Cash Flow'!I11 -> -39.914668 | J12: ='Cash Flow'!J11 -> -45.531391 | K12: ='Cash Flow'!K11 -> -75.68 | L12: ='Cash Flow'!L11 -> -53.922 | M12: ='Cash Flow'!M11 -> -20.812 | ... O12: ='Cash Flow'!O11 -> 0
B13: Free cash flow to the firm | F13: =F9+F10+F11+F12 -> 617.41797 | G13: =G9+G10+G11+G12 -> 558.47708 | H13: =H9+H10+H11+H12 -> 493.20322 | I13: =I9+I10+I11+I12 -> 970.59022 | J13: =J9+J10+J11+J12 -> 1439.7748 | K13: =K9+K10+K11+K12 -> 1924.916 | L13: =L9+L10+L11+L12 -> 2369.2826 | M13: =M9+M10+M11+M12 -> 2565.9522 | ... O13: =O9+O10+O11+O12 -> 2639.8751
B14: Discount period (mid-year, years) | F14: 0.5 | G14: 1.5 | H14: 2.5 | I14: 3.5 | J14: 4.5 | K14: 5.5 | L14: 6.5 | M14: 7.5 | N14: 8.5 | O14: 9.5
B15: Discount factor | F15: =1/(1+Assumptions!$C$33)^F14 -> 0.95835617 | G15: =1/(1+Assumptions!$C$33)^G14 -> 0.8801989 | H15: =1/(1+Assumptions!$C$33)^H14 -> 0.80841564 | I15: =1/(1+Assumptions!$C$33)^I14 -> 0.74248654 | J15: =1/(1+Assumptions!$C$33)^J14 -> 0.6819342 | K15: =1/(1+Assumptions!$C$33)^K14 -> 0.6263201 | L15: =1/(1+Assumptions!$C$33)^L14 -> 0.57524153 | M15: =1/(1+Assumptions!$C$33)^M14 -> 0.52832859 | ... O15: =1/(1+Assumptions!$C$33)^O14 -> 0.44566844
B16: PV of FCFF | F16: =F13*F15 -> 591.70632 | G16: =G13*G15 -> 491.57091 | H16: =H13*H15 -> 398.7132 | I16: =I13*I15 -> 720.65018 | J16: =J13*J15 -> 981.83166 | K16: =K13*K15 -> 1205.6136 | L16: =L13*L15 -> 1362.9098 | M16: =M13*M15 -> 1355.6659 | ... O16: =O13*O15 -> 1176.509
B18: Enterprise and equity value
B19: Sum of PV of explicit forecast FCFF | C19: =SUM(F16:O16) -> 9565.9087
B20: Terminal growth rate | C20: =Assumptions!$C$36 -> 0.025
B21: Terminal year FCFF | C21: =O13 -> 2639.8751
B22: Cumulative ore mined to FY36 (Mt) | C22: =SUM(Deck!F34:O34)/1000/Assumptions!$C$54 -> 103.96002
B23: Ore base remaining after FY36 (Mt) | C23: =MAX(0,Assumptions!$C$50-C22) -> 230.53998
B24: Terminal mining rate (Mt ore p.a.) | C24: =Deck!O34/1000/Assumptions!$C$54 -> 14.280222
B25: Remaining mine life (years) | C25: =MIN(Assumptions!$C$55,IFERROR(C23/C24,0)) -> 16.144006 | E25: The terminal value is an annuity over remaining ore, not a perpetuity: an orebody is finite
B26: Terminal annuity factor | C26: =(1-(1+Assumptions!$C$33)^-C25)/Assumptions!$C$33 -> 8.4098716
B27: Terminal value at end of forecast | C27: =C21*C26 -> 22201.011
B28: PV of terminal value | C28: =C27*O15 -> 9894.2898
B29: Enterprise value | C29: =C19+C28 -> 19460.198
B30: Terminal value as % of EV | C30: =C28/C29 -> 0.50843725 | E30: A lower share means less of the answer rests on the terminal assumption
B31: Add: net cash / (net debt) | C31: =Assumptions!$C$21 -> 1462
B32: Equity value | C32: =C29+C31 -> 20922.198
B33: Shares on issue (m) | C33: =Assumptions!$C$12 -> 3220
B34: Value per share (A$) | C34: =C32/C33 -> 6.4975772
B35: Last close (A$) | C35: =Assumptions!$C$11 -> 5.48
B36: Implied upside / (downside) | C36: =C34/C35-1 -> 0.18568926
B38: Mid-year convention assumes cash flows arrive evenly through each financial year. The stub from the 5-Sep-26 valuation date to 30-Jun-27 is not discounted separately; the effect is immaterial at this WACC.

Sheet Scenario Engine
B2: Scenario engine
B3: A compact FCFF for each case, computed directly off the Deck's three scenario blocks, so all three values are live at once. The detailed statements show whichever case the switch selects.
B4: PLS Group Limited (ASX: PLS) | Valuation date 5 September 2026 | All figures A$ unless stated
B6: BEAR CASE (A$m unless stated) | C6: FY24A | D6: FY25A | E6: FY26A | F6: FY27F | G6: FY28F | H6: FY29F | I6: FY30F | J6: FY31F | K6: FY32F | L6: FY33F | M6: FY34F | N6: FY35F | O6: FY36F
B7: Concentrate sold (kt) | F7: =Deck!F12 -> 1030 | G7: =Deck!G12 -> 1050 | H7: =Deck!H12 -> 1030 | I7: =Deck!I12 -> 990 | J7: =Deck!J12 -> 980 | K7: =Deck!K12 -> 1000 | L7: =Deck!L12 -> 1000 | M7: =Deck!M12 -> 1010 | ... O7: =Deck!O12 -> 1020
B8: Realised price (US$/t) | F8: =Deck!F38 -> 1350 | G8: =Deck!G38 -> 1150 | H8: =Deck!H38 -> 1050 | I8: =Deck!I38 -> 1050 | J8: =Deck!J38 -> 1150 | K8: =Deck!K38 -> 1250 | L8: =Deck!L38 -> 1350 | M8: =Deck!M38 -> 1450 | ... O8: =Deck!O38 -> 1550
B9: Realised price (A$/t) | F9: =F8/Deck!F42 -> 2045.4545 | G9: =G8/Deck!G42 -> 1716.4179 | H9: =H8/Deck!H42 -> 1544.1176 | I9: =I8/Deck!I42 -> 1521.7391 | J9: =J8/Deck!J42 -> 1642.8571 | K9: =K8/Deck!K42 -> 1785.7143 | L9: =L8/Deck!L42 -> 1928.5714 | M9: =M8/Deck!M42 -> 2071.4286 | ... O9: =O8/Deck!O42 -> 2214.2857
B10: Unit operating cost (A$/t) | F10: =Deck!F46 -> 625 | G10: =Deck!G46 -> 645 | H10: =Deck!H46 -> 655 | I10: =Deck!I46 -> 640 | J10: =Deck!J46 -> 625 | K10: =Deck!K46 -> 615 | L10: =Deck!L46 -> 610 | M10: =Deck!M46 -> 610 | ... O10: =Deck!O46 -> 610
B11: Revenue | F11: =F7*F9/1000*(1-'Revenue Build'!F20) -> 1993.05 | G11: =G7*G9/1000*(1-'Revenue Build'!G20) -> 1704.9179 | H11: =H7*H9/1000*(1-'Revenue Build'!H20) -> 1504.5574 | I11: =I7*I9/1000*(1-'Revenue Build'!I20) -> 1425.1696 | J11: =J7*J9/1000*(1-'Revenue Build'!J20) -> 1523.06 | K11: =K7*K9/1000*(1-'Revenue Build'!K20) -> 1689.2857 | L11: =L7*L9/1000*(1-'Revenue Build'!L20) -> 1824.4286 | M11: =M7*M9/1000*(1-'Revenue Build'!M20) -> 1979.1671 | ... O11: =O7*O9/1000*(1-'Revenue Build'!O20) -> 2136.6086
B12: Operating costs | F12: =-F7*F10/1000 -> -643.75 | G12: =-G7*G10/1000 -> -677.25 | H12: =-H7*H10/1000 -> -674.65 | I12: =-I7*I10/1000 -> -633.6 | J12: =-J7*J10/1000 -> -612.5 | K12: =-K7*K10/1000 -> -615 | L12: =-L7*L10/1000 -> -610 | M12: =-M7*M10/1000 -> -616.1 | ... O12: =-O7*O10/1000 -> -622.2
B13: Royalties | F13: =-F11*Assumptions!$C$42 -> -99.6525 | G13: =-G11*Assumptions!$C$42 -> -85.245896 | H13: =-H11*Assumptions!$C$42 -> -75.227868 | I13: =-I11*Assumptions!$C$42 -> -71.258478 | J13: =-J11*Assumptions!$C$42 -> -76.153 | K13: =-K11*Assumptions!$C$42 -> -84.464286 | L13: =-L11*Assumptions!$C$42 -> -91.221429 | M13: =-M11*Assumptions!$C$42 -> -98.958357 | ... O13: =-O11*Assumptions!$C$42 -> -106.83043
B14: Corporate and admin | F14: =-Assumptions!$C$40*(1+Assumptions!$C$41)^(0) -> -95 | G14: =-Assumptions!$C$40*(1+Assumptions!$C$41)^(1) -> -97.375 | H14: =-Assumptions!$C$40*(1+Assumptions!$C$41)^(2) -> -99.809375 | I14: =-Assumptions!$C$40*(1+Assumptions!$C$41)^(3) -> -102.30461 | J14: =-Assumptions!$C$40*(1+Assumptions!$C$41)^(4) -> -104.86222 | K14: =-Assumptions!$C$40*(1+Assumptions!$C$41)^(5) -> -107.48378 | L14: =-Assumptions!$C$40*(1+Assumptions!$C$41)^(6) -> -110.17087 | M14: =-Assumptions!$C$40*(1+Assumptions!$C$41)^(7) -> -112.92515 | N14: =-Assumptions!$C$40*(1+Assumptions!$C$41)^(8) -> -115.74828 | O14: =-Assumptions!$C$40*(1+Assumptions!$C$41)^(9) -> -118.64198
B15: EBITDA | F15: =SUM(F11:F14) -> 1154.6475 | G15: =SUM(G11:G14) -> 845.04701 | H15: =SUM(H11:H14) -> 654.87011 | I15: =SUM(I11:I14) -> 618.00648 | J15: =SUM(J11:J14) -> 729.54478 | K15: =SUM(K11:K14) -> 882.33765 | L15: =SUM(L11:L14) -> 1013.0363 | M15: =SUM(M11:M14) -> 1151.1836 | ... O15: =SUM(O11:O14) -> 1288.9362
B16: Capital expenditure | F16: =Deck!F54 -> 620 | G16: =Deck!G54 -> 400 | H16: =Deck!H54 -> 340 | I16: =Deck!I54 -> 320 | J16: =Deck!J54 -> 300 | K16: =Deck!K54 -> 295 | L16: =Deck!L54 -> 290 | M16: =Deck!M54 -> 290 | ... O16: =Deck!O54 -> 290
B17: PP&E (closing) | F17: ='Balance Sheet'!E15+F16-F18 -> 3452 | G17: =F17+G16-G18 -> 3455.02 | H17: =G17+H16-H18 -> 3397.6927 | I17: =H17+I16-I18 -> 3326.958 | J17: =I17+J16-J18 -> 3244.3579 | K17: =J17+K16-K18 -> 3166.2567 | L17: =K17+L16-L18 -> 3092.1372 | M17: =L17+M16-M18 -> 3026.5414 | N17: =M17+N16-N18 -> 2968.4891 | O17: =N17+O16-O18 -> 2917.1129
B18: D&A | F18: ='Balance Sheet'!E15*'Balance Sheet'!F8 -> 368 | G18: =F17*'Balance Sheet'!F8 -> 396.98 | H18: =G17*'Balance Sheet'!F8 -> 397.3273 | I18: =H17*'Balance Sheet'!F8 -> 390.73466 | J18: =I17*'Balance Sheet'!F8 -> 382.60017 | K18: =J17*'Balance Sheet'!F8 -> 373.10115 | L18: =K17*'Balance Sheet'!F8 -> 364.11952 | M18: =L17*'Balance Sheet'!F8 -> 355.59578 | N18: =M17*'Balance Sheet'!F8 -> 348.05226 | O18: =N17*'Balance Sheet'!F8 -> 341.37625
B19: EBIT | F19: =F15-F18 -> 786.6475 | G19: =G15-G18 -> 448.06701 | H19: =H15-H18 -> 257.54281 | I19: =I15-I18 -> 227.27182 | J19: =J15-J18 -> 346.9446 | K19: =K15-K18 -> 509.23649 | L19: =L15-L18 -> 648.91675 | M19: =M15-M18 -> 795.58786 | ... O19: =O15-O18 -> 947.55991
B20: NOPAT | F20: =F19*(1-Assumptions!$C$31) -> 550.65325 | G20: =G19*(1-Assumptions!$C$31) -> 313.64691 | H20: =H19*(1-Assumptions!$C$31) -> 180.27997 | I20: =I19*(1-Assumptions!$C$31) -> 159.09027 | J20: =J19*(1-Assumptions!$C$31) -> 242.86122 | K20: =K19*(1-Assumptions!$C$31) -> 356.46555 | L20: =L19*(1-Assumptions!$C$31) -> 454.24172 | M20: =M19*(1-Assumptions!$C$31) -> 556.9115 | ... O20: =O19*(1-Assumptions!$C$31) -> 663.29194
B21: Movement in net working capital | F21: =-(F11*Assumptions!$C$44-'Balance Sheet'!E14) -> -4.7302759 | G21: =-(G11*Assumptions!$C$44-F11*Assumptions!$C$44) -> 23.050567 | H21: =-(H11*Assumptions!$C$44-G11*Assumptions!$C$44) -> 16.028845 | I21: =-(I11*Assumptions!$C$44-H11*Assumptions!$C$44) -> 6.351023 | J21: =-(J11*Assumptions!$C$44-I11*Assumptions!$C$44) -> -7.8312348 | K21: =-(K11*Assumptions!$C$44-J11*Assumptions!$C$44) -> -13.298057 | L21: =-(L11*Assumptions!$C$44-K11*Assumptions!$C$44) -> -10.811429 | M21: =-(M11*Assumptions!$C$44-L11*Assumptions!$C$44) -> -12.379086 | N21: =-(N11*Assumptions!$C$44-M11*Assumptions!$C$44) -> -7.0814857 | O21: =-(O11*Assumptions!$C$44-N11*Assumptions!$C$44) -> -5.5138286
B22: FCFF | F22: =F20+F18-F16+F21 -> 293.92297 | G22: =G20+G18-G16+G21 -> 333.67748 | H22: =H20+H18-H16+H21 -> 253.63611 | I22: =I20+I18-I16+I21 -> 236.17596 | J22: =J20+J18-J16+J21 -> 317.63016 | K22: =K20+K18-K16+K21 -> 421.26864 | L22: =L20+L18-L16+L21 -> 517.54982 | M22: =M20+M18-M16+M21 -> 610.12819 | ... O22: =O20+O18-O16+O21 -> 709.15436
B23: Discount factor | F23: =1/(1+Assumptions!$C$33)^(DCF!F14) -> 0.95835617 | G23: =1/(1+Assumptions!$C$33)^(DCF!G14) -> 0.8801989 | H23: =1/(1+Assumptions!$C$33)^(DCF!H14) -> 0.80841564 | I23: =1/(1+Assumptions!$C$33)^(DCF!I14) -> 0.74248654 | J23: =1/(1+Assumptions!$C$33)^(DCF!J14) -> 0.6819342 | K23: =1/(1+Assumptions!$C$33)^(DCF!K14) -> 0.6263201 | L23: =1/(1+Assumptions!$C$33)^(DCF!L14) -> 0.57524153 | M23: =1/(1+Assumptions!$C$33)^(DCF!M14) -> 0.52832859 | ... O23: =1/(1+Assumptions!$C$33)^(DCF!O14) -> 0.44566844
B24: PV of FCFF | F24: =F22*F23 -> 281.68289 | G24: =G22*G23 -> 293.70255 | H24: =H22*H23 -> 205.0434 | I24: =I22*I23 -> 175.35747 | J24: =J22*J23 -> 216.60287 | K24: =K22*K23 -> 263.84902 | L24: =L22*L23 -> 297.71615 | M24: =M22*M23 -> 322.34817 | ... O24: =O22*O23 -> 316.04772
B25: PV of explicit FCFF | C25: =SUM(F24:O24) -> 2695.415
B26: Terminal growth | C26: 0.015
B27: Cumulative ore mined to FY36 (Mt) | C27: =SUM(F7:O7)/1000/Assumptions!$C$54 -> 57.863459
B28: Ore base remaining after FY36 (Mt) | C28: =MAX(0,Assumptions!$C$50-C27) -> 276.63654
B29: Terminal mining rate (Mt ore p.a.) | C29: =O7/1000/Assumptions!$C$54 -> 5.8263305
B30: Remaining mine life (years) | C30: =MIN(Assumptions!$C$55,IFERROR(C28/C29,0)) -> 25
B31: Terminal annuity factor | C31: =(1-(1+Assumptions!$C$33)^-C30)/Assumptions!$C$33 -> 9.9192586
B32: PV of terminal value | C32: =O22*C31*O23 -> 3134.959
B33: Memo: growing perpetuity alternative | C33: =O22*(1+C26)/(Assumptions!$C$33-C26)*O23 -> 4347.0212
B34: Enterprise value | C34: =C25+C32 -> 5830.3741
B35: Net cash | C35: =Assumptions!$C$21 -> 1462
B36: Equity value | C36: =C34+C35 -> 7292.3741
B37: Value per share (A$) | C37: =C36/Assumptions!$C$12 -> 2.2647124
B38: Upside to last close | C38: =C37/Assumptions!$C$11-1 -> -0.58673131
B41: BASE CASE (A$m unless stated) | C41: FY24A | D41: FY25A | E41: FY26A | F41: FY27F | G41: FY28F | H41: FY29F | I41: FY30F | J41: FY31F | K41: FY32F | L41: FY33F | M41: FY34F | N41: FY35F | O41: FY36F
B42: Concentrate sold (kt) | F42: =Deck!F19 -> 1065 | G42: =Deck!G19 -> 1115 | H42: =Deck!H19 -> 1115 | I42: =Deck!I19 -> 1365 | J42: =Deck!J19 -> 1665 | K42: =Deck!K19 -> 2065 | L42: =Deck!L19 -> 2350 | M42: =Deck!M19 -> 2460 | ... O42: =Deck!O19 -> 2500
B43: Realised price (US$/t) | F43: =Deck!F39 -> 1700 | G43: =Deck!G39 -> 1780 | H43: =Deck!H39 -> 1850 | I43: =Deck!I39 -> 1800 | J43: =Deck!J39 -> 1750 | K43: =Deck!K39 -> 1750 | L43: =Deck!L39 -> 1750 | M43: =Deck!M39 -> 1750 | ... O43: =Deck!O39 -> 1750
B44: Realised price (A$/t) | F44: =F43/Deck!F42 -> 2575.7576 | G44: =G43/Deck!G42 -> 2656.7164 | H44: =H43/Deck!H42 -> 2720.5882 | I44: =I43/Deck!I42 -> 2608.6957 | J44: =J43/Deck!J42 -> 2500 | K44: =K43/Deck!K42 -> 2500 | L44: =L43/Deck!L42 -> 2500 | M44: =M43/Deck!M42 -> 2500 | ... O44: =O43/Deck!O42 -> 2500
B45: Unit operating cost (A$/t) | F45: =Deck!F47 -> 600 | G45: =Deck!G47 -> 590 | H45: =Deck!H47 -> 585 | I45: =Deck!I47 -> 580 | J45: =Deck!J47 -> 570 | K45: =Deck!K47 -> 565 | L45: =Deck!L47 -> 565 | M45: =Deck!M47 -> 565 | ... O45: =Deck!O47 -> 565
B46: Revenue | F46: =F42*F44/1000*(1-'Revenue Build'!F20) -> 2595.05 | G46: =G42*G44/1000*(1-'Revenue Build'!G20) -> 2802.2779 | H46: =H42*H44/1000*(1-'Revenue Build'!H20) -> 2869.6493 | I46: =I42*I44/1000*(1-'Revenue Build'!I20) -> 3368.5826 | J46: =J42*J44/1000*(1-'Revenue Build'!J20) -> 3937.725 | K46: =K42*K44/1000*(1-'Revenue Build'!K20) -> 4883.725 | L46: =L42*L44/1000*(1-'Revenue Build'!L20) -> 5557.75 | M46: =M42*M44/1000*(1-'Revenue Build'!M20) -> 5817.9 | ... O46: =O42*O44/1000*(1-'Revenue Build'!O20) -> 5912.5
B47: Operating costs | F47: =-F42*F45/1000 -> -639 | G47: =-G42*G45/1000 -> -657.85 | H47: =-H42*H45/1000 -> -652.275 | I47: =-I42*I45/1000 -> -791.7 | J47: =-J42*J45/1000 -> -949.05 | K47: =-K42*K45/1000 -> -1166.725 | L47: =-L42*L45/1000 -> -1327.75 | M47: =-M42*M45/1000 -> -1389.9 | ... O47: =-O42*O45/1000 -> -1412.5
B48: Royalties | F48: =-F46*Assumptions!$C$42 -> -129.7525 | G48: =-G46*Assumptions!$C$42 -> -140.1139 | H48: =-H46*Assumptions!$C$42 -> -143.48246 | I48: =-I46*Assumptions!$C$42 -> -168.42913 | J48: =-J46*Assumptions!$C$42 -> -196.88625 | K48: =-K46*Assumptions!$C$42 -> -244.18625 | L48: =-L46*Assumptions!$C$42 -> -277.8875 | M48: =-M46*Assumptions!$C$42 -> -290.895 | ... O48: =-O46*Assumptions!$C$42 -> -295.625
B49: Corporate and admin | F49: =-Assumptions!$C$40*(1+Assumptions!$C$41)^(0) -> -95 | G49: =-Assumptions!$C$40*(1+Assumptions!$C$41)^(1) -> -97.375 | H49: =-Assumptions!$C$40*(1+Assumptions!$C$41)^(2) -> -99.809375 | I49: =-Assumptions!$C$40*(1+Assumptions!$C$41)^(3) -> -102.30461 | J49: =-Assumptions!$C$40*(1+Assumptions!$C$41)^(4) -> -104.86222 | K49: =-Assumptions!$C$40*(1+Assumptions!$C$41)^(5) -> -107.48378 | L49: =-Assumptions!$C$40*(1+Assumptions!$C$41)^(6) -> -110.17087 | M49: =-Assumptions!$C$40*(1+Assumptions!$C$41)^(7) -> -112.92515 | N49: =-Assumptions!$C$40*(1+Assumptions!$C$41)^(8) -> -115.74828 | O49: =-Assumptions!$C$40*(1+Assumptions!$C$41)^(9) -> -118.64198
B50: EBITDA | F50: =SUM(F46:F49) -> 1731.2975 | G50: =SUM(G46:G49) -> 1906.939 | H50: =SUM(H46:H49) -> 1974.0824 | I50: =SUM(I46:I49) -> 2306.1489 | J50: =SUM(J46:J49) -> 2686.9265 | K50: =SUM(K46:K49) -> 3365.33 | L50: =SUM(L46:L49) -> 3841.9416 | M50: =SUM(M46:M49) -> 4024.1799 | ... O50: =SUM(O46:O49) -> 4085.733
B51: Capital expenditure | F51: =Deck!F55 -> 652 | G51: =Deck!G55 -> 880 | H51: =Deck!H55 -> 1020 | I51: =Deck!I55 -> 760 | J51: =Deck!J55 -> 560 | K51: =Deck!K55 -> 520 | L51: =Deck!L55 -> 430 | M51: =Deck!M55 -> 390 | ... O51: =Deck!O55 -> 370
B52: PP&E (closing) | F52: ='Balance Sheet'!E15+F51-F53 -> 3484 | G52: =F52+G51-G53 -> 3963.34 | H52: =G52+H51-H53 -> 4527.5559 | I52: =H52+I51-I53 -> 4766.887 | J52: =I52+J51-J53 -> 4778.695 | K52: =J52+K51-K53 -> 4749.145 | L52: =K52+L51-L53 -> 4632.9934 | M52: =L52+M51-M53 -> 4490.1991 | N52: =M52+N51-N53 -> 4343.8262 | O52: =N52+O51-O53 -> 4214.2862
B53: D&A | F53: ='Balance Sheet'!E15*'Balance Sheet'!F8 -> 368 | G53: =F52*'Balance Sheet'!F8 -> 400.66 | H53: =G52*'Balance Sheet'!F8 -> 455.7841 | I53: =H52*'Balance Sheet'!F8 -> 520.66893 | J53: =I52*'Balance Sheet'!F8 -> 548.192 | K53: =J52*'Balance Sheet'!F8 -> 549.54992 | L53: =K52*'Balance Sheet'!F8 -> 546.15168 | M53: =L52*'Balance Sheet'!F8 -> 532.79424 | N53: =M52*'Balance Sheet'!F8 -> 516.3729 | O53: =N52*'Balance Sheet'!F8 -> 499.54002
B54: EBIT | F54: =F50-F53 -> 1363.2975 | G54: =G50-G53 -> 1506.279 | H54: =H50-H53 -> 1518.2983 | I54: =I50-I53 -> 1785.4799 | J54: =J50-J53 -> 2138.7345 | K54: =K50-K53 -> 2815.78 | L54: =L50-L53 -> 3295.7899 | M54: =M50-M53 -> 3491.3856 | ... O54: =O50-O53 -> 3586.193
B55: NOPAT | F55: =F54*(1-Assumptions!$C$31) -> 954.30825 | G55: =G54*(1-Assumptions!$C$31) -> 1054.3953 | H55: =H54*(1-Assumptions!$C$31) -> 1062.8088 | I55: =I54*(1-Assumptions!$C$31) -> 1249.836 | J55: =J54*(1-Assumptions!$C$31) -> 1497.1142 | K55: =K54*(1-Assumptions!$C$31) -> 1971.046 | L55: =L54*(1-Assumptions!$C$31) -> 2307.053 | M55: =M54*(1-Assumptions!$C$31) -> 2443.9699 | ... O55: =O54*(1-Assumptions!$C$31) -> 2510.3351
B56: Movement in net working capital | F56: =-(F46*Assumptions!$C$44-'Balance Sheet'!E14) -> -52.890276 | G56: =-(G46*Assumptions!$C$44-F46*Assumptions!$C$44) -> -16.578233 | H56: =-(H46*Assumptions!$C$44-G46*Assumptions!$C$44) -> -5.3897083 | I56: =-(I46*Assumptions!$C$44-H46*Assumptions!$C$44) -> -39.914668 | J56: =-(J46*Assumptions!$C$44-I46*Assumptions!$C$44) -> -45.531391 | K56: =-(K46*Assumptions!$C$44-J46*Assumptions!$C$44) -> -75.68 | L56: =-(L46*Assumptions!$C$44-K46*Assumptions!$C$44) -> -53.922 | M56: =-(M46*Assumptions!$C$44-L46*Assumptions!$C$44) -> -20.812 | N56: =-(N46*Assumptions!$C$44-M46*Assumptions!$C$44) -> -7.568 | O56: =-(O46*Assumptions!$C$44-N46*Assumptions!$C$44) -> 0
B57: FCFF | F57: =F55+F53-F51+F56 -> 617.41797 | G57: =G55+G53-G51+G56 -> 558.47708 | H57: =H55+H53-H51+H56 -> 493.20322 | I57: =I55+I53-I51+I56 -> 970.59022 | J57: =J55+J53-J51+J56 -> 1439.7748 | K57: =K55+K53-K51+K56 -> 1924.916 | L57: =L55+L53-L51+L56 -> 2369.2826 | M57: =M55+M53-M51+M56 -> 2565.9522 | ... O57: =O55+O53-O51+O56 -> 2639.8751
B58: Discount factor | F58: =1/(1+Assumptions!$C$33)^(DCF!F14) -> 0.95835617 | G58: =1/(1+Assumptions!$C$33)^(DCF!G14) -> 0.8801989 | H58: =1/(1+Assumptions!$C$33)^(DCF!H14) -> 0.80841564 | I58: =1/(1+Assumptions!$C$33)^(DCF!I14) -> 0.74248654 | J58: =1/(1+Assumptions!$C$33)^(DCF!J14) -> 0.6819342 | K58: =1/(1+Assumptions!$C$33)^(DCF!K14) -> 0.6263201 | L58: =1/(1+Assumptions!$C$33)^(DCF!L14) -> 0.57524153 | M58: =1/(1+Assumptions!$C$33)^(DCF!M14) -> 0.52832859 | ... O58: =1/(1+Assumptions!$C$33)^(DCF!O14) -> 0.44566844
B59: PV of FCFF | F59: =F57*F58 -> 591.70632 | G59: =G57*G58 -> 491.57091 | H59: =H57*H58 -> 398.7132 | I59: =I57*I58 -> 720.65018 | J59: =J57*J58 -> 981.83166 | K59: =K57*K58 -> 1205.6136 | L59: =L57*L58 -> 1362.9098 | M59: =M57*M58 -> 1355.6659 | ... O59: =O57*O58 -> 1176.509
B60: PV of explicit FCFF | C60: =SUM(F59:O59) -> 9565.9087
B61: Terminal growth | C61: 0.025
B62: Cumulative ore mined to FY36 (Mt) | C62: =SUM(F42:O42)/1000/Assumptions!$C$54 -> 103.96002
B63: Ore base remaining after FY36 (Mt) | C63: =MAX(0,Assumptions!$C$50-C62) -> 230.53998
B64: Terminal mining rate (Mt ore p.a.) | C64: =O42/1000/Assumptions!$C$54 -> 14.280222
B65: Remaining mine life (years) | C65: =MIN(Assumptions!$C$55,IFERROR(C63/C64,0)) -> 16.144006
B66: Terminal annuity factor | C66: =(1-(1+Assumptions!$C$33)^-C65)/Assumptions!$C$33 -> 8.4098716
B67: PV of terminal value | C67: =O57*C66*O58 -> 9894.2898
B68: Memo: growing perpetuity alternative | C68: =O57*(1+C61)/(Assumptions!$C$33-C61)*O58 -> 18903.076
B69: Enterprise value | C69: =C60+C67 -> 19460.198
B70: Net cash | C70: =Assumptions!$C$21 -> 1462
B71: Equity value | C71: =C69+C70 -> 20922.198
B72: Value per share (A$) | C72: =C71/Assumptions!$C$12 -> 6.4975772
B73: Upside to last close | C73: =C72/Assumptions!$C$11-1 -> 0.18568926
B76: BULL CASE (A$m unless stated) | C76: FY24A | D76: FY25A | E76: FY26A | F76: FY27F | G76: FY28F | H76: FY29F | I76: FY30F | J76: FY31F | K76: FY32F | L76: FY33F | M76: FY34F | N76: FY35F | O76: FY36F
B77: Concentrate sold (kt) | F77: =Deck!F26 -> 1100 | G77: =Deck!G26 -> 1165 | H77: =Deck!H26 -> 1295 | I77: =Deck!I26 -> 1625 | J77: =Deck!J26 -> 2135 | K77: =Deck!K26 -> 2480 | L77: =Deck!L26 -> 2625 | M77: =Deck!M26 -> 2685 | ... O77: =Deck!O26 -> 2685
B78: Realised price (US$/t) | F78: =Deck!F40 -> 2050 | G78: =Deck!G40 -> 2400 | H78: =Deck!H40 -> 2600 | I78: =Deck!I40 -> 2450 | J78: =Deck!J40 -> 2300 | K78: =Deck!K40 -> 2150 | L78: =Deck!L40 -> 2050 | M78: =Deck!M40 -> 1975 | ... O78: =Deck!O40 -> 1900
B79: Realised price (A$/t) | F79: =F78/Deck!F42 -> 3106.0606 | G79: =G78/Deck!G42 -> 3582.0896 | H79: =H78/Deck!H42 -> 3823.5294 | I79: =I78/Deck!I42 -> 3550.7246 | J79: =J78/Deck!J42 -> 3285.7143 | K79: =K78/Deck!K42 -> 3071.4286 | L79: =L78/Deck!L42 -> 2928.5714 | M79: =M78/Deck!M42 -> 2821.4286 | ... O79: =O78/Deck!O42 -> 2714.2857
B80: Unit operating cost (A$/t) | F80: =Deck!F48 -> 585 | G80: =Deck!G48 -> 565 | H80: =Deck!H48 -> 550 | I80: =Deck!I48 -> 540 | J80: =Deck!J48 -> 530 | K80: =Deck!K48 -> 525 | L80: =Deck!L48 -> 520 | M80: =Deck!M48 -> 520 | ... O80: =Deck!O48 -> 520
B81: Revenue | F81: =F77*F79/1000*(1-'Revenue Build'!F20) -> 3232.1667 | G81: =G77*G79/1000*(1-'Revenue Build'!G20) -> 3947.7851 | H81: =H77*H79/1000*(1-'Revenue Build'!H20) -> 4684.0912 | I81: =I77*I79/1000*(1-'Revenue Build'!I20) -> 5458.3514 | J81: =J77*J79/1000*(1-'Revenue Build'!J20) -> 6636.19 | K81: =K77*K79/1000*(1-'Revenue Build'!K20) -> 7205.8171 | L81: =L77*L79/1000*(1-'Revenue Build'!L20) -> 7272.375 | M81: =M77*M79/1000*(1-'Revenue Build'!M20) -> 7166.4568 | ... O81: =O77*O79/1000*(1-'Revenue Build'!O20) -> 6894.3129
B82: Operating costs | F82: =-F77*F80/1000 -> -643.5 | G82: =-G77*G80/1000 -> -658.225 | H82: =-H77*H80/1000 -> -712.25 | I82: =-I77*I80/1000 -> -877.5 | J82: =-J77*J80/1000 -> -1131.55 | K82: =-K77*K80/1000 -> -1302 | L82: =-L77*L80/1000 -> -1365 | M82: =-M77*M80/1000 -> -1396.2 | ... O82: =-O77*O80/1000 -> -1396.2
B83: Royalties | F83: =-F81*Assumptions!$C$42 -> -161.60833 | G83: =-G81*Assumptions!$C$42 -> -197.38925 | H83: =-H81*Assumptions!$C$42 -> -234.20456 | I83: =-I81*Assumptions!$C$42 -> -272.91757 | J83: =-J81*Assumptions!$C$42 -> -331.8095 | K83: =-K81*Assumptions!$C$42 -> -360.29086 | L83: =-L81*Assumptions!$C$42 -> -363.61875 | M83: =-M81*Assumptions!$C$42 -> -358.32284 | ... O83: =-O81*Assumptions!$C$42 -> -344.71564
B84: Corporate and admin | F84: =-Assumptions!$C$40*(1+Assumptions!$C$41)^(0) -> -95 | G84: =-Assumptions!$C$40*(1+Assumptions!$C$41)^(1) -> -97.375 | H84: =-Assumptions!$C$40*(1+Assumptions!$C$41)^(2) -> -99.809375 | I84: =-Assumptions!$C$40*(1+Assumptions!$C$41)^(3) -> -102.30461 | J84: =-Assumptions!$C$40*(1+Assumptions!$C$41)^(4) -> -104.86222 | K84: =-Assumptions!$C$40*(1+Assumptions!$C$41)^(5) -> -107.48378 | L84: =-Assumptions!$C$40*(1+Assumptions!$C$41)^(6) -> -110.17087 | M84: =-Assumptions!$C$40*(1+Assumptions!$C$41)^(7) -> -112.92515 | N84: =-Assumptions!$C$40*(1+Assumptions!$C$41)^(8) -> -115.74828 | O84: =-Assumptions!$C$40*(1+Assumptions!$C$41)^(9) -> -118.64198
B85: EBITDA | F85: =SUM(F81:F84) -> 2332.0583 | G85: =SUM(G81:G84) -> 2994.7958 | H85: =SUM(H81:H84) -> 3637.8272 | I85: =SUM(I81:I84) -> 4205.6293 | J85: =SUM(J81:J84) -> 5067.9683 | K85: =SUM(K81:K84) -> 5436.0425 | L85: =SUM(L81:L84) -> 5433.5854 | M85: =SUM(M81:M84) -> 5299.0088 | ... O85: =SUM(O81:O84) -> 5034.7552
B86: Capital expenditure | F86: =Deck!F56 -> 685 | G86: =Deck!G56 -> 1020 | H86: =Deck!H56 -> 1130 | I86: =Deck!I56 -> 900 | J86: =Deck!J56 -> 720 | K86: =Deck!K56 -> 600 | L86: =Deck!L56 -> 480 | M86: =Deck!M56 -> 430 | ... O86: =Deck!O56 -> 410
B87: PP&E (closing) | F87: ='Balance Sheet'!E15+F86-F88 -> 3517 | G87: =F87+G86-G88 -> 4132.545 | H87: =G87+H86-H88 -> 4787.3023 | I87: =H87+I86-I88 -> 5136.7626 | J87: =I87+J86-J88 -> 5266.0349 | K87: =J87+K86-K88 -> 5260.4409 | L87: =K87+L86-L88 -> 5135.4902 | M87: =L87+M86-M88 -> 4974.9088 | N87: =M87+N86-N88 -> 4812.7943 | O87: =N87+O86-O88 -> 4669.3229
B88: D&A | F88: ='Balance Sheet'!E15*'Balance Sheet'!F8 -> 368 | G88: =F87*'Balance Sheet'!F8 -> 404.455 | H88: =G87*'Balance Sheet'!F8 -> 475.24268 | I88: =H87*'Balance Sheet'!F8 -> 550.53977 | J88: =I87*'Balance Sheet'!F8 -> 590.72769 | K88: =J87*'Balance Sheet'!F8 -> 605.59401 | L88: =K87*'Balance Sheet'!F8 -> 604.9507 | M88: =L87*'Balance Sheet'!F8 -> 590.58137 | N88: =M87*'Balance Sheet'!F8 -> 572.11451 | O88: =N87*'Balance Sheet'!F8 -> 553.47134
B89: EBIT | F89: =F85-F88 -> 1964.0583 | G89: =G85-G88 -> 2590.3408 | H89: =H85-H88 -> 3162.5846 | I89: =I85-I88 -> 3655.0895 | J89: =J85-J88 -> 4477.2406 | K89: =K85-K88 -> 4830.4485 | L89: =L85-L88 -> 4828.6347 | M89: =M85-M88 -> 4708.4274 | ... O89: =O85-O88 -> 4481.2839
B90: NOPAT | F90: =F89*(1-Assumptions!$C$31) -> 1374.8408 | G90: =G89*(1-Assumptions!$C$31) -> 1813.2386 | H90: =H89*(1-Assumptions!$C$31) -> 2213.8092 | I90: =I89*(1-Assumptions!$C$31) -> 2558.5627 | J90: =J89*(1-Assumptions!$C$31) -> 3134.0684 | K90: =K89*(1-Assumptions!$C$31) -> 3381.3139 | L90: =L89*(1-Assumptions!$C$31) -> 3380.0443 | M90: =M89*(1-Assumptions!$C$31) -> 3295.8992 | ... O90: =O89*(1-Assumptions!$C$31) -> 3136.8987
B91: Movement in net working capital | F91: =-(F81*Assumptions!$C$44-'Balance Sheet'!E14) -> -103.85961 | G91: =-(G81*Assumptions!$C$44-F81*Assumptions!$C$44) -> -57.249473 | H91: =-(H81*Assumptions!$C$44-G81*Assumptions!$C$44) -> -58.904488 | I91: =-(I81*Assumptions!$C$44-H81*Assumptions!$C$44) -> -61.940822 | J91: =-(J81*Assumptions!$C$44-I81*Assumptions!$C$44) -> -94.227084 | K91: =-(K81*Assumptions!$C$44-J81*Assumptions!$C$44) -> -45.570171 | L91: =-(L81*Assumptions!$C$44-K81*Assumptions!$C$44) -> -5.3246286 | M91: =-(M81*Assumptions!$C$44-L81*Assumptions!$C$44) -> 8.4734571 | N91: =-(N81*Assumptions!$C$44-M81*Assumptions!$C$44) -> 14.514343 | O91: =-(O81*Assumptions!$C$44-N81*Assumptions!$C$44) -> 7.2571714
B92: FCFF | F92: =F90+F88-F86+F91 -> 953.98122 | G92: =G90+G88-G86+G91 -> 1140.4441 | H92: =H90+H88-H86+H91 -> 1500.1474 | I92: =I90+I88-I86+I91 -> 2147.1616 | J92: =J90+J88-J86+J91 -> 2910.569 | K92: =K90+K88-K86+K91 -> 3341.3378 | L92: =L90+L88-L86+L91 -> 3499.6703 | M92: =M90+M88-M86+M91 -> 3464.954 | ... O92: =O90+O88-O86+O91 -> 3287.6272
B93: Discount factor | F93: =1/(1+Assumptions!$C$33)^(DCF!F14) -> 0.95835617 | G93: =1/(1+Assumptions!$C$33)^(DCF!G14) -> 0.8801989 | H93: =1/(1+Assumptions!$C$33)^(DCF!H14) -> 0.80841564 | I93: =1/(1+Assumptions!$C$33)^(DCF!I14) -> 0.74248654 | J93: =1/(1+Assumptions!$C$33)^(DCF!J14) -> 0.6819342 | K93: =1/(1+Assumptions!$C$33)^(DCF!K14) -> 0.6263201 | L93: =1/(1+Assumptions!$C$33)^(DCF!L14) -> 0.57524153 | M93: =1/(1+Assumptions!$C$33)^(DCF!M14) -> 0.52832859 | ... O93: =1/(1+Assumptions!$C$33)^(DCF!O14) -> 0.44566844
B94: PV of FCFF | F94: =F92*F93 -> 914.25379 | G94: =G92*G93 -> 1003.8176 | H94: =H92*H93 -> 1212.7426 | I94: =I92*I93 -> 1594.2386 | J94: =J92*J93 -> 1984.8165 | K94: =K92*K93 -> 2092.747 | L94: =L92*L93 -> 2013.1557 | M94: =M92*M93 -> 1830.6343 | ... O94: =O92*O93 -> 1465.1917
B95: PV of explicit FCFF | C95: =SUM(F94:O94) -> 15743.382
B96: Terminal growth | C96: 0.03
B97: Cumulative ore mined to FY36 (Mt) | C97: =SUM(F77:O77)/1000/Assumptions!$C$54 -> 116.98358
B98: Ore base remaining after FY36 (Mt) | C98: =MAX(0,Assumptions!$C$50-C97) -> 217.51642
B99: Terminal mining rate (Mt ore p.a.) | C99: =O77/1000/Assumptions!$C$54 -> 15.336958
B100: Remaining mine life (years) | C100: =MIN(Assumptions!$C$55,IFERROR(C98/C99,0)) -> 14.182501
B101: Terminal annuity factor | C101: =(1-(1+Assumptions!$C$33)^-C100)/Assumptions!$C$33 -> 7.8919478
B102: PV of terminal value | C102: =O92*C101*O93 -> 11563.216
B103: Memo: growing perpetuity alternative | C103: =O92*(1+C96)/(Assumptions!$C$33-C96)*O93 -> 25667.956
B104: Enterprise value | C104: =C95+C102 -> 27306.598
B105: Net cash | C105: =Assumptions!$C$21 -> 1462
B106: Equity value | C106: =C104+C105 -> 28768.598
...

Sheet Scenario Summary
B2: Scenario summary
B3: All three cases valued live, then probability weighted
B4: PLS Group Limited (ASX: PLS) | Valuation date 5 September 2026 | All figures A$ unless stated
C6: Bear | D6: Base | E6: Bull | F6: Weighted
B7: Probability weighting | C7: 0.25 | D7: 0.5 | E7: 0.25 | F7: =SUM(C7:E7) -> 1
B8: Enterprise value (A$m) | C8: ='Scenario Engine'!$C$34 -> 5830.3741 | D8: ='Scenario Engine'!$C$69 -> 19460.198 | E8: ='Scenario Engine'!$C$104 -> 27306.598 | F8: =SUMPRODUCT(C8:E8,C$7:E$7) -> 18014.342
B9: Equity value (A$m) | C9: ='Scenario Engine'!$C$36 -> 7292.3741 | D9: ='Scenario Engine'!$C$71 -> 20922.198 | E9: ='Scenario Engine'!$C$106 -> 28768.598 | F9: =SUMPRODUCT(C9:E9,C$7:E$7) -> 19476.342
B10: Value per share (A$) | C10: ='Scenario Engine'!$C$37 -> 2.2647124 | D10: ='Scenario Engine'!$C$72 -> 6.4975772 | E10: ='Scenario Engine'!$C$107 -> 8.9343473 | F10: =SUMPRODUCT(C10:E10,C$7:E$7) -> 6.0485535
B11: Upside / (downside) to last close | C11: ='Scenario Engine'!$C$38 -> -0.58673131 | D11: ='Scenario Engine'!$C$73 -> 0.18568926 | E11: ='Scenario Engine'!$C$108 -> 0.63035535 | F11: =SUMPRODUCT(C11:E11,C$7:E$7) -> 0.10375064
B13: Operating metrics at FY30
B14: Concentrate sold (kt) | C14: ='Scenario Engine'!I7 -> 990 | D14: ='Scenario Engine'!I42 -> 1365 | E14: ='Scenario Engine'!I77 -> 1625
B15: Realised price (US$/t) | C15: ='Scenario Engine'!I8 -> 1050 | D15: ='Scenario Engine'!I43 -> 1800 | E15: ='Scenario Engine'!I78 -> 2450
B16: Unit cost (A$/t) | C16: ='Scenario Engine'!I10 -> 640 | D16: ='Scenario Engine'!I45 -> 580 | E16: ='Scenario Engine'!I80 -> 540
B17: EBITDA (A$m) | C17: ='Scenario Engine'!I15 -> 618.00648 | D17: ='Scenario Engine'!I50 -> 2306.1489 | E17: ='Scenario Engine'!I85 -> 4205.6293
B19: Narrative
B20: Bear | C20: Restart supply from Bald Hill, Finniss and Jianxiawo overwhelms demand. Price reverts toward the 90th-percentile cash cost. No P2000 FID, no Colina, Ngungaju re-idled from FY30.
B21: Base | C21: Prices ease from the June-2026 quarter peak as restart tonnes land, then recover as the surplus narrows. P2000 is sanctioned in late 2026 for first ore mid-2029; Colina follows the Dec-2027 study.
B22: Bull | C22: The 2027-29 deficit called by Fastmarkets, Morgan Stanley and UBS arrives. Prices clear at the level needed to fund new supply. P2000 and Colina both proceed, on schedule.

Sheet Sensitivity
B2: Sensitivity analysis
B3: Base-case value per share under alternative cost of capital, growth, price and cost
B4: PLS Group Limited (ASX: PLS) | Valuation date 5 September 2026 | All figures A$ unless stated
B6: 1. Value per share (A$) - WACC vs remaining mine life
B7: Remaining mine life (yrs) \ WACC | C7: 0.0788 | D7: 0.0838 | E7: 0.0888 | F7: 0.0938 | G7: 0.0988
B8: 10 | C8: =(SUMPRODUCT('Scenario Engine'!F57:O57,1/(1+C$7)^DCF!F14:O14)+'Scenario Engine'!O57*(1-(1+C$7)^-$B8)/C$7/(1+C$7)^DCF!O14+Assumptions!$C$21)/Assumptions!$C$12 -> 6.2833439 | D8: =(SUMPRODUCT('Scenario Engine'!F57:O57,1/(1+D$7)^DCF!F14:O14)+'Scenario Engine'!O57*(1-(1+D$7)^-$B8)/D$7/(1+D$7)^DCF!O14+Assumptions!$C$21)/Assumptions!$C$12 -> 6.0249514 | E8: =(SUMPRODUCT('Scenario Engine'!F57:O57,1/(1+E$7)^DCF!F14:O14)+'Scenario Engine'!O57*(1-(1+E$7)^-$B8)/E$7/(1+E$7)^DCF!O14+Assumptions!$C$21)/Assumptions!$C$12 -> 5.7819238 | F8: =(SUMPRODUCT('Scenario Engine'!F57:O57,1/(1+F$7)^DCF!F14:O14)+'Scenario Engine'!O57*(1-(1+F$7)^-$B8)/F$7/(1+F$7)^DCF!O14+Assumptions!$C$21)/Assumptions!$C$12 -> 5.5531848 | G8: =(SUMPRODUCT('Scenario Engine'!F57:O57,1/(1+G$7)^DCF!F14:O14)+'Scenario Engine'!O57*(1-(1+G$7)^-$B8)/G$7/(1+G$7)^DCF!O14+Assumptions!$C$21)/Assumptions!$C$12 -> 5.3377427
B9: 15 | C9: =(SUMPRODUCT('Scenario Engine'!F57:O57,1/(1+C$7)^DCF!F14:O14)+'Scenario Engine'!O57*(1-(1+C$7)^-$B9)/C$7/(1+C$7)^DCF!O14+Assumptions!$C$21)/Assumptions!$C$12 -> 7.031551 | D9: =(SUMPRODUCT('Scenario Engine'!F57:O57,1/(1+D$7)^DCF!F14:O14)+'Scenario Engine'!O57*(1-(1+D$7)^-$B9)/D$7/(1+D$7)^DCF!O14+Assumptions!$C$21)/Assumptions!$C$12 -> 6.6997128 | E9: =(SUMPRODUCT('Scenario Engine'!F57:O57,1/(1+E$7)^DCF!F14:O14)+'Scenario Engine'!O57*(1-(1+E$7)^-$B9)/E$7/(1+E$7)^DCF!O14+Assumptions!$C$21)/Assumptions!$C$12 -> 6.3907642 | F9: =(SUMPRODUCT('Scenario Engine'!F57:O57,1/(1+F$7)^DCF!F14:O14)+'Scenario Engine'!O57*(1-(1+F$7)^-$B9)/F$7/(1+F$7)^DCF!O14+Assumptions!$C$21)/Assumptions!$C$12 -> 6.1028261 | G9: =(SUMPRODUCT('Scenario Engine'!F57:O57,1/(1+G$7)^DCF!F14:O14)+'Scenario Engine'!O57*(1-(1+G$7)^-$B9)/G$7/(1+G$7)^DCF!O14+Assumptions!$C$21)/Assumptions!$C$12 -> 5.8341931
B10: 20 | C10: =(SUMPRODUCT('Scenario Engine'!F57:O57,1/(1+C$7)^DCF!F14:O14)+'Scenario Engine'!O57*(1-(1+C$7)^-$B10)/C$7/(1+C$7)^DCF!O14+Assumptions!$C$21)/Assumptions!$C$12 -> 7.5436067 | D10: =(SUMPRODUCT('Scenario Engine'!F57:O57,1/(1+D$7)^DCF!F14:O14)+'Scenario Engine'!O57*(1-(1+D$7)^-$B10)/D$7/(1+D$7)^DCF!O14+Assumptions!$C$21)/Assumptions!$C$12 -> 7.1509497 | E10: =(SUMPRODUCT('Scenario Engine'!F57:O57,1/(1+E$7)^DCF!F14:O14)+'Scenario Engine'!O57*(1-(1+E$7)^-$B10)/E$7/(1+E$7)^DCF!O14+Assumptions!$C$21)/Assumptions!$C$12 -> 6.7886541 | F10: =(SUMPRODUCT('Scenario Engine'!F57:O57,1/(1+F$7)^DCF!F14:O14)+'Scenario Engine'!O57*(1-(1+F$7)^-$B10)/F$7/(1+F$7)^DCF!O14+Assumptions!$C$21)/Assumptions!$C$12 -> 6.4538929 | G10: =(SUMPRODUCT('Scenario Engine'!F57:O57,1/(1+G$7)^DCF!F14:O14)+'Scenario Engine'!O57*(1-(1+G$7)^-$B10)/G$7/(1+G$7)^DCF!O14+Assumptions!$C$21)/Assumptions!$C$12 -> 6.1441366
B11: 25 | C11: =(SUMPRODUCT('Scenario Engine'!F57:O57,1/(1+C$7)^DCF!F14:O14)+'Scenario Engine'!O57*(1-(1+C$7)^-$B11)/C$7/(1+C$7)^DCF!O14+Assumptions!$C$21)/Assumptions!$C$12 -> 7.8940457 | D11: =(SUMPRODUCT('Scenario Engine'!F57:O57,1/(1+D$7)^DCF!F14:O14)+'Scenario Engine'!O57*(1-(1+D$7)^-$B11)/D$7/(1+D$7)^DCF!O14+Assumptions!$C$21)/Assumptions!$C$12 -> 7.4527077 | E11: =(SUMPRODUCT('Scenario Engine'!F57:O57,1/(1+E$7)^DCF!F14:O14)+'Scenario Engine'!O57*(1-(1+E$7)^-$B11)/E$7/(1+E$7)^DCF!O14+Assumptions!$C$21)/Assumptions!$C$12 -> 7.0486835 | F11: =(SUMPRODUCT('Scenario Engine'!F57:O57,1/(1+F$7)^DCF!F14:O14)+'Scenario Engine'!O57*(1-(1+F$7)^-$B11)/F$7/(1+F$7)^DCF!O14+Assumptions!$C$21)/Assumptions!$C$12 -> 6.6781262 | G11: =(SUMPRODUCT('Scenario Engine'!F57:O57,1/(1+G$7)^DCF!F14:O14)+'Scenario Engine'!O57*(1-(1+G$7)^-$B11)/G$7/(1+G$7)^DCF!O14+Assumptions!$C$21)/Assumptions!$C$12 -> 6.3376403
B12: 30 | C12: =(SUMPRODUCT('Scenario Engine'!F57:O57,1/(1+C$7)^DCF!F14:O14)+'Scenario Engine'!O57*(1-(1+C$7)^-$B12)/C$7/(1+C$7)^DCF!O14+Assumptions!$C$21)/Assumptions!$C$12 -> 8.1338781 | D12: =(SUMPRODUCT('Scenario Engine'!F57:O57,1/(1+D$7)^DCF!F14:O14)+'Scenario Engine'!O57*(1-(1+D$7)^-$B12)/D$7/(1+D$7)^DCF!O14+Assumptions!$C$21)/Assumptions!$C$12 -> 7.6545039 | E12: =(SUMPRODUCT('Scenario Engine'!F57:O57,1/(1+E$7)^DCF!F14:O14)+'Scenario Engine'!O57*(1-(1+E$7)^-$B12)/E$7/(1+E$7)^DCF!O14+Assumptions!$C$21)/Assumptions!$C$12 -> 7.2186181 | F12: =(SUMPRODUCT('Scenario Engine'!F57:O57,1/(1+F$7)^DCF!F14:O14)+'Scenario Engine'!O57*(1-(1+F$7)^-$B12)/F$7/(1+F$7)^DCF!O14+Assumptions!$C$21)/Assumptions!$C$12 -> 6.8213485 | G12: =(SUMPRODUCT('Scenario Engine'!F57:O57,1/(1+G$7)^DCF!F14:O14)+'Scenario Engine'!O57*(1-(1+G$7)^-$B12)/G$7/(1+G$7)^DCF!O14+Assumptions!$C$21)/Assumptions!$C$12 -> 6.4584483
B14: Base case sits at WACC 8.88% and a terminal life derived from the remaining ore base (highlighted).
B16: 2. Linear price and cost sensitivity coefficients
B17: Base case, per forecast year | C17: FY24A | D17: FY25A | E17: FY26A | F17: FY27F | G17: FY28F | H17: FY29F | I17: FY30F | J17: FY31F | K17: FY32F | L17: FY33F | M17: FY34F | N17: FY35F | O17: FY36F
B18: Concentrate sold (kt) | F18: ='Scenario Engine'!F42 -> 1065 | G18: ='Scenario Engine'!G42 -> 1115 | H18: ='Scenario Engine'!H42 -> 1115 | I18: ='Scenario Engine'!I42 -> 1365 | J18: ='Scenario Engine'!J42 -> 1665 | K18: ='Scenario Engine'!K42 -> 2065 | L18: ='Scenario Engine'!L42 -> 2350 | M18: ='Scenario Engine'!M42 -> 2460 | ... O18: ='Scenario Engine'!O42 -> 2500
B19: Realised price (A$/t) | F19: ='Scenario Engine'!F44 -> 2575.7576 | G19: ='Scenario Engine'!G44 -> 2656.7164 | H19: ='Scenario Engine'!H44 -> 2720.5882 | I19: ='Scenario Engine'!I44 -> 2608.6957 | J19: ='Scenario Engine'!J44 -> 2500 | K19: ='Scenario Engine'!K44 -> 2500 | L19: ='Scenario Engine'!L44 -> 2500 | M19: ='Scenario Engine'!M44 -> 2500 | ... O19: ='Scenario Engine'!O44 -> 2500
B20: Unit cost (A$/t) | F20: ='Scenario Engine'!F45 -> 600 | G20: ='Scenario Engine'!G45 -> 590 | H20: ='Scenario Engine'!H45 -> 585 | I20: ='Scenario Engine'!I45 -> 580 | J20: ='Scenario Engine'!J45 -> 570 | K20: ='Scenario Engine'!K45 -> 565 | L20: ='Scenario Engine'!L45 -> 565 | M20: ='Scenario Engine'!M45 -> 565 | ... O20: ='Scenario Engine'!O45 -> 565
B21: Discount factor | F21: ='Scenario Engine'!F58 -> 0.95835617 | G21: ='Scenario Engine'!G58 -> 0.8801989 | H21: ='Scenario Engine'!H58 -> 0.80841564 | I21: ='Scenario Engine'!I58 -> 0.74248654 | J21: ='Scenario Engine'!J58 -> 0.6819342 | K21: ='Scenario Engine'!K58 -> 0.6263201 | L21: ='Scenario Engine'!L58 -> 0.57524153 | M21: ='Scenario Engine'!M58 -> 0.52832859 | ... O21: ='Scenario Engine'!O58 -> 0.44566844
B22: PV of a 100% price change (A$m) | F22: =F18/1000*F19*(1-'Revenue Build'!F20)*(1-Assumptions!$C$42)*(1-Assumptions!$C$31)*F21 -> 1653.8431 | G22: =G18/1000*G19*(1-'Revenue Build'!G20)*(1-Assumptions!$C$42)*(1-Assumptions!$C$31)*G21 -> 1640.2637 | H22: =H18/1000*H19*(1-'Revenue Build'!H20)*(1-Assumptions!$C$42)*(1-Assumptions!$C$31)*H21 -> 1542.7131 | I22: =I18/1000*I19*(1-'Revenue Build'!I20)*(1-Assumptions!$C$42)*(1-Assumptions!$C$31)*I21 -> 1663.2496 | J22: =J18/1000*J19*(1-'Revenue Build'!J20)*(1-Assumptions!$C$42)*(1-Assumptions!$C$31)*J21 -> 1785.7041 | K22: =K18/1000*K19*(1-'Revenue Build'!K20)*(1-Assumptions!$C$42)*(1-Assumptions!$C$31)*K21 -> 2034.0855 | L22: =L18/1000*L19*(1-'Revenue Build'!L20)*(1-Assumptions!$C$42)*(1-Assumptions!$C$31)*L21 -> 2126.0373 | M22: =M18/1000*M19*(1-'Revenue Build'!M20)*(1-Assumptions!$C$42)*(1-Assumptions!$C$31)*M21 -> 2044.0523 | ... O22: =O18/1000*O19*(1-'Revenue Build'!O20)*(1-Assumptions!$C$42)*(1-Assumptions!$C$31)*O21 -> 1752.2847
B23: PV of a 100% unit-cost change (A$m) | F23: =F18/1000*F20*(1-Assumptions!$C$31)*F21 -> 428.67271 | G23: =G18/1000*G20*(1-Assumptions!$C$31)*G21 -> 405.32719 | H23: =H18/1000*H20*(1-Assumptions!$C$31)*H21 -> 369.11652 | I23: =I18/1000*I20*(1-Assumptions!$C$31)*I21 -> 411.47862 | J23: =J18/1000*J20*(1-Assumptions!$C$31)*J21 -> 453.03276 | K23: =K18/1000*K20*(1-Assumptions!$C$31)*K21 -> 511.52033 | L23: =L18/1000*L20*(1-Assumptions!$C$31)*L21 -> 534.64386 | M23: =M18/1000*M20*(1-Assumptions!$C$31)*M21 -> 514.02674 | ... O23: =O18/1000*O20*(1-Assumptions!$C$31)*O21 -> 440.65467
B25: Price coefficient K(price), incl. terminal value | C25: =SUM(F22:O22)+O22*(1+Assumptions!$C$36)/(Assumptions!$C$33-Assumptions!$C$36) -> 46304.229
B26: Cost coefficient K(cost), incl. terminal value | C26: =SUM(F23:O23)+O23*(1+Assumptions!$C$36)/(Assumptions!$C$33-Assumptions!$C$36) -> 11628.294
B28: 3. Value per share (A$) - realised price vs unit operating cost
B29: Unit cost change \ Realised price change | C29: -0.2 | D29: -0.1 | E29: 0 | F29: 0.1 | G29: 0.2
B30: -0.1 | C30: ='Scenario Engine'!$C$72+($C$25*C$29-$C$26*$B30)/Assumptions!$C$12 -> 3.9826652 | D30: ='Scenario Engine'!$C$72+($C$25*D$29-$C$26*$B30)/Assumptions!$C$12 -> 5.4206848 | E30: ='Scenario Engine'!$C$72+($C$25*E$29-$C$26*$B30)/Assumptions!$C$12 -> 6.8587043 | F30: ='Scenario Engine'!$C$72+($C$25*F$29-$C$26*$B30)/Assumptions!$C$12 -> 8.2967238 | G30: ='Scenario Engine'!$C$72+($C$25*G$29-$C$26*$B30)/Assumptions!$C$12 -> 9.7347434
B31: -0.05 | C31: ='Scenario Engine'!$C$72+($C$25*C$29-$C$26*$B31)/Assumptions!$C$12 -> 3.8021017 | D31: ='Scenario Engine'!$C$72+($C$25*D$29-$C$26*$B31)/Assumptions!$C$12 -> 5.2401212 | E31: ='Scenario Engine'!$C$72+($C$25*E$29-$C$26*$B31)/Assumptions!$C$12 -> 6.6781407 | F31: ='Scenario Engine'!$C$72+($C$25*F$29-$C$26*$B31)/Assumptions!$C$12 -> 8.1161603 | G31: ='Scenario Engine'!$C$72+($C$25*G$29-$C$26*$B31)/Assumptions!$C$12 -> 9.5541798
B32: 0 | C32: ='Scenario Engine'!$C$72+($C$25*C$29-$C$26*$B32)/Assumptions!$C$12 -> 3.6215381 | D32: ='Scenario Engine'!$C$72+($C$25*D$29-$C$26*$B32)/Assumptions!$C$12 -> 5.0595576 | E32: ='Scenario Engine'!$C$72+($C$25*E$29-$C$26*$B32)/Assumptions!$C$12 -> 6.4975772 | F32: ='Scenario Engine'!$C$72+($C$25*F$29-$C$26*$B32)/Assumptions!$C$12 -> 7.9355967 | G32: ='Scenario Engine'!$C$72+($C$25*G$29-$C$26*$B32)/Assumptions!$C$12 -> 9.3736162
B33: 0.05 | C33: ='Scenario Engine'!$C$72+($C$25*C$29-$C$26*$B33)/Assumptions!$C$12 -> 3.4409745 | D33: ='Scenario Engine'!$C$72+($C$25*D$29-$C$26*$B33)/Assumptions!$C$12 -> 4.8789941 | E33: ='Scenario Engine'!$C$72+($C$25*E$29-$C$26*$B33)/Assumptions!$C$12 -> 6.3170136 | F33: ='Scenario Engine'!$C$72+($C$25*F$29-$C$26*$B33)/Assumptions!$C$12 -> 7.7550331 | G33: ='Scenario Engine'!$C$72+($C$25*G$29-$C$26*$B33)/Assumptions!$C$12 -> 9.1930527
B34: 0.1 | C34: ='Scenario Engine'!$C$72+($C$25*C$29-$C$26*$B34)/Assumptions!$C$12 -> 3.2604109 | D34: ='Scenario Engine'!$C$72+($C$25*D$29-$C$26*$B34)/Assumptions!$C$12 -> 4.6984305 | E34: ='Scenario Engine'!$C$72+($C$25*E$29-$C$26*$B34)/Assumptions!$C$12 -> 6.13645 | F34: ='Scenario Engine'!$C$72+($C$25*F$29-$C$26*$B34)/Assumptions!$C$12 -> 7.5744695 | G34: ='Scenario Engine'!$C$72+($C$25*G$29-$C$26*$B34)/Assumptions!$C$12 -> 9.0124891
B36: Grid 3 applies a proportional shift to every forecast year. It flows price through the realisation adjustment, royalty and tax, and captures the effect on terminal value; it holds volume, capex and working capital unchanged.
B37: Read across the top row of grid 3 for the commodity call, and down the left column for operational delivery. The pitch stands or falls on the top-left quadrant.

Sheet SOTP NAV
B2: Sum of the parts
B3: Risked net asset value as a cross-check on the consolidated DCF
B4: PLS Group Limited (ASX: PLS) | Valuation date 5 September 2026 | All figures A$ unless stated
B6: Asset | C6: Unrisked A$m | D6: Risking | E6: Risked A$m | F6: A$/share | G6: Basis
B7: Pilgangoora - Pilgan plant | C7: 9800 | D7: 1 | E7: =C7*D7 -> 9800 | F7: =E7/Assumptions!$C$12 -> 3.0434783 | G7: In production, ~920ktpa steady state. Carried at the DCF value of the producing base.
B8: Ngungaju plant | C8: 1450 | D8: 0.95 | E8: =C8*D8 -> 1377.5 | F8: =E8/Assumptions!$C$12 -> 0.42779503 | G8: Restarted July 2026, ~195ktpa. Small risking for ramp-up execution.
B9: P2000 expansion | C9: 2600 | D9: 0.7 | E9: =C9*D9 -> 1820 | F9: =E9/Assumptions!$C$12 -> 0.56521739 | G9: PFS incremental NPV A$2.6bn, 55% IRR. Risked for an FID that has not been taken; DFS due Dec-qtr 2026.
B10: Colina, Brazil | C10: 900 | D10: 0.4 | E10: =C10*D10 -> 360 | F10: =E10/Assumptions!$C$12 -> 0.11180124 | G10: 77.7Mt at 1.24% Li2O. DFS only due Dec-qtr 2027, no FID, no permits. Heavily risked.
B11: Mid-stream plant (Calix) | C11: 260 | D11: 0.5 | E11: =C11*D11 -> 130 | F11: =E11/Assumptions!$C$12 -> 0.040372671 | G11: Demonstration scale, opened Jun-26, first production guided Sep-qtr 2026. Optionality, not yet earnings.
B12: POSCO JV, 18% of PPLS | C12: 320 | D12: 0.85 | E12: =C12*D12 -> 272 | F12: =E12/Assumptions!$C$12 -> 0.08447205 | G12: 18% of a 43ktpa lithium hydroxide facility at Gwangyang, with an option to move to 30%.
B13: Exploration and other tenements | C13: 180 | D13: 0.5 | E13: =C13*D13 -> 90 | F13: =E13/Assumptions!$C$12 -> 0.027950311 | G13: Includes the tenements acquired adjacent to Colina.
B14: Corporate costs, capitalised | C14: -900 | D14: 1 | E14: =C14*D14 -> -900 | F14: =E14/Assumptions!$C$12 -> -0.27950311 | G14: Present value of unallocated corporate and administration costs.
B15: Enterprise NAV | E15: =SUM(E7:E14) -> 12949.5 | F15: =E15/Assumptions!$C$12 -> 4.0215839
B16: Net cash | E16: =Assumptions!$C$21 -> 1462 | F16: =E16/Assumptions!$C$12 -> 0.45403727
B17: Equity NAV | E17: =E15+E16 -> 14411.5 | F17: =E17/Assumptions!$C$12 -> 4.4756211
B18: Premium / (discount) of last close to NAV | F18: =Assumptions!$C$11/F17-1 -> 0.22441106
B20: The SOTP is a cross-check, not the primary method. Asset NPVs are our own estimates built from the same
B21: price deck and discount rate as the consolidated DCF, except P2000 which uses the company's own PFS figure.
B22: Risk weightings are judgement: P2000 at 70% reflects a study due in the December 2026 quarter and a board
B23: that has already committed A$175m of pre-FID capital; Colina at 40% reflects a study still a year further out.

Sheet Trading Comps
B2: Trading comparables
B3: The case's own six-stock peer set, then lithium pure-plays
B4: PLS Group Limited (ASX: PLS) | Valuation date 5 September 2026 | All figures A$ unless stated
B6: The case peer set (figures as reported around Aug-Sep 2026; vendors disagree - see Sources)
B7: Company | C7: Commodity exposure | D7: Mkt cap A$m | E7: EV A$m | F7: FY26 EBITDA A$m | G7: EV/EBITDA | H7: P/E fwd | I7: Div yield | J7: Consensus
B8: BHP Group | C8: Iron ore, copper, met coal, potash | D8: 312560 | E8: 343660 | F8: 50600 | G8: n/a | H8: 17.38 | I8: 0.0431 | J8: Hold
B9: Rio Tinto | C9: Iron ore, aluminium, copper, lithium | D9: 220530 | E9: 247680 | F9: 45500 | G9: 7.84 | H9: 11.7 | I9: 0.0355 | J9: Hold
B10: Fortescue | C10: Iron ore, green energy | D10: 68680 | E10: 70150 | F10: 13230 | G10: 5.55 | H10: 14.72 | I10: 0.07 | J10: Neutral
B11: South32 | C11: Alumina, aluminium, base metals | D11: 17190 | E11: 17150 | F11: 3790 | G11: 8.48 | H11: 18.2 | I11: 0.0249 | J11: Buy
B12: Mineral Resources | C12: Lithium, iron ore, mining services | D12: 10400 | E12: 15720 | F12: 2600 | G12: 7.82 | H12: 15.5 | I12: n/a | J12: Buy
B13: Peer median | G13: =MEDIAN(G8:G12) -> 7.83 | H13: =MEDIAN(H8:H12) -> 15.5 | I13: =MEDIAN(I8:I12) -> 0.0393
B15: PLS Group valued against the peer median
B16: FY27E EBITDA, base case (A$m) | D16: ='Scenario Engine'!F50 -> 1731.2975
B17: Multiple applied - low | D17: 8
B18: Multiple applied - high | D18: 11
B19: Implied value per share - low (A$) | D19: =(D16*D17+Assumptions!$C$21)/Assumptions!$C$12 -> 4.7553975
B20: Implied value per share - high (A$) | D20: =(D16*D18+Assumptions!$C$21)/Assumptions!$C$12 -> 6.3684076
B21: Midpoint (A$) | D21: =AVERAGE(D19,D20) -> 5.5619026
B23: Why a premium to the diversified peer median is warranted, and why it is capped.
B24: PLS is not a mature cash-return miner. Base-case volumes rise from 1,065kt in FY27 to 2,350kt by FY33, so a
B25: single-year forward multiple understates it - the diversified peers on this page are growing volumes at low
B26: single digits. Against that, PLS carries single-commodity risk and a price series that has moved by a factor of
B27: three inside two years. We therefore apply 8.0x to 11.0x, a premium to the ~7.8x peer median but well below the
B28: 26.8x PLS itself traded at on trailing FY26 EBITDA before the earnings recovery came through.

Sheet Precedents
B2: Precedent transactions
B3: Lithium M&A, 2023-2026
B4: PLS Group Limited (ASX: PLS) | Valuation date 5 September 2026 | All figures A$ unless stated
B6: Completed | C6: Acquirer | D6: Target | E6: Value | F6: Structure | G6: Rationale and terms
B7: Mar-2025 | C7: Rio Tinto | D7: Arcadium Lithium | E7: US$6.7bn | F7: All cash | G7: US$5.85/share. Rio becomes the third-largest global lithium producer; adds Rincon, Olaroz, Mt Cattlin, Fenix, James Bay.
B8: Jan-2025 | C8: PLS Group | D8: Latin Resources | E8: A$560m | F8: All scrip | G8: 0.07 PLS shares per LRS share. Adds the Colina project in Brazil and preserves PLS's net cash position.
B9: May-2026 | C9: Zhejiang Huayou Cobalt | D9: Atlantic Lithium | E9: US$210m | F9: All cash | G9: US$0.25486/share, a 26.6% premium. Reported explicitly as a price-rebound-driven acquisition of Ewoyaa, Ghana.
B10: Aug-2025 | C10: Sayona Mining | D10: Piedmont Lithium | E10: n/d | F10: Merger of equals | G10: 50/50 equity split creating Elevra Lithium. Both were sub-scale standalone through the price trough.
B11: May-2024 | C11: SQM and Hancock | D11: Azure Minerals | E11: A$1.7bn | F11: Scheme, cash | G11: A$3.70/share. Gives SQM its first Australian hard-rock foothold at Andover.
B12: Oct-2023 | C12: Albemarle (withdrawn) | D12: Liontown Resources | E12: A$6.6bn | F12: Cash, lapsed | G12: A$3.00/share, nearly double the pre-bid price. Collapsed after Hancock built a 19.9% blocking stake.
B13: Jan-2024 | C13: Livent | D13: Allkem | E13: US$10.6bn | F13: Merger of equals | G13: Created Arcadium Lithium, the entity Rio Tinto acquired 14 months later.
B14: Oct-2025 | C14: Ganfeng Lithium | D14: Leo Lithium (Goulamina 40%) | E14: US$343m | F14: Staged cash | G14: Consolidates operating control of Goulamina in Mali, plus a 1.5% gross revenue royalty for 20 years.
B16: Applying a control premium to PLS
B17: Base-case value per share (A$) | E17: ='Scenario Engine'!$C$72 -> 6.4975772
B18: Control premium observed in completed lithium deals | E18: 0.266 | G18: Huayou / Atlantic Lithium, May-2026, the most recent completed cash deal with a disclosed premium
B19: Implied takeout value per share (A$) | E19: =E17*(1+E18) -> 8.2259327
B21: A control premium is a reference point, not our target. PLS at ~A$17.6bn is large for this sector: the biggest
B22: completed lithium deal on this page, Rio Tinto and Arcadium, was US$6.7bn. Consolidation in 2026 has run through
B23: sub-scale developers rather than producers of PLS's size. We show the premium to frame downside support, not to
B24: argue PLS is a target.
B25: EV/resource multiples were deliberately left out: the disclosed resource statements for these targets are not on a
B26: consistent basis (JORC vs exploration target, ore tonnes vs LCE), so any multiple built from them would be spurious.

Sheet Football Field
B2: Valuation summary
B3: Range by methodology, and the weighted 12-month target price
B4: PLS Group Limited (ASX: PLS) | Valuation date 5 September 2026 | All figures A$ unless stated
B6: Methodology | C6: Low (A$) | D6: High (A$) | E6: Midpoint | F6: Weight | G6: Basis
B7: DCF - base case | C7: ='Scenario Engine'!$C$72 -> 6.4975772 | D7: ='Scenario Engine'!$C$72 -> 6.4975772 | E7: =AVERAGE(C7:D7) -> 6.4975772 | F7: 0.6 | G7: WACC 8.88% built from the case's prescribed CAPM inputs. Terminal value is an annuity over the remaining ore base, not a growing perpetuity - an orebody is finite
B8: DCF - probability weighted (25/50/25) | C8: ='Scenario Summary'!$F$10 -> 6.0485535 | D8: ='Scenario Summary'!$F$10 -> 6.0485535 | E8: =AVERAGE(C8:D8) -> 6.0485535 | F8: 0 | G8: Reference. Shown so the reader can see what the bear case does to the expected value
B9: DCF - scenario range | C9: ='Scenario Engine'!$C$37 -> 2.2647124 | D9: ='Scenario Engine'!$C$107 -> 8.9343473 | E9: =AVERAGE(C9:D9) -> 5.5995299 | F9: 0 | G9: Bear to bull. Shown to frame asymmetry - the point estimate above already sits inside this range
B10: Trading comparables | C10: ='Trading Comps'!$D$19 -> 4.7553975 | D10: ='Trading Comps'!$D$20 -> 6.3684076 | E10: =AVERAGE(C10:D10) -> 5.5619026 | F10: 0.4 | G10: 8.0x to 11.0x FY27E EBITDA against a diversified peer median near 7.8x
B11: Precedent transactions | C11: ='Scenario Engine'!$C$72 -> 6.4975772 | D11: =Precedents!$E$19 -> 8.2259327 | E11: =AVERAGE(C11:D11) -> 7.3617549 | F11: 0 | G11: Reference only. Transaction EV/EBITDA could not be sourced on a consistent basis, and applying a premium to our own DCF would be circular
B12: Broker target range (individual analysts) | C12: 2.5 | D12: 6.83 | E12: =AVERAGE(C12:D12) -> 4.665 | F12: 0 | G12: Full individual spread across 17-20 analysts, Aug-Sep 2026. Vendor averages cluster A$4.50-5.70; our A$6.12 sits inside the individual range, below the most bullish. Reference only
B13: 52-week trading range | C13: 1.91 | D13: 6.81 | E13: =AVERAGE(C13:D13) -> 4.36 | F13: 0 | G13: Where the market has actually traded - reference only
B14: Total weight | F14: =SUM(F7:F13) -> 1
B16: 12-month target price (A$) | C16: =SUMPRODUCT(E7:E13,F7:F13)/SUM(F7:F13) -> 6.1233073
B17: Last close (A$) | C17: =Assumptions!$C$11 -> 5.48
B18: Implied upside / (downside) | C18: =C16/C17-1 -> 0.11739185
B19: Plus forecast FY27 dividend yield | C19: ='Income Statement'!F25 -> 0.016698836
B20: Implied 12-month total return | C20: =C18+C19 -> 0.13409068
B21: S&P/ASX 200 return, FY26 (benchmark) | C21: =Assumptions!$C$58 -> 0.059
B22: Implied outperformance | C22: =C20-C21 -> 0.075090683
B24: The DCF carries 60% because it is the only method that prices the volume growth from P2000 and Colina. Comparables carry 40% as the discipline of what the market pays for a producing miner today. Precedents, consensus and the trading range are shown but not weighted.

Sheet ESG Value Bridge
B2: Shared value bridge
B3: Converting each ESG lever into A$ per share, so the shared-value case is priced rather than asserted
B4: PLS Group Limited (ASX: PLS) | Valuation date 5 September 2026 | All figures A$ unless stated
B6: PV of A$1/t of sustained unit-margin improvement
B7: Concentrate sold, base case (kt) | F7: ='Scenario Engine'!F42 -> 1065 | G7: ='Scenario Engine'!G42 -> 1115 | H7: ='Scenario Engine'!H42 -> 1115 | I7: ='Scenario Engine'!I42 -> 1365 | J7: ='Scenario Engine'!J42 -> 1665 | K7: ='Scenario Engine'!K42 -> 2065 | L7: ='Scenario Engine'!L42 -> 2350 | M7: ='Scenario Engine'!M42 -> 2460 | ... O7: ='Scenario Engine'!O42 -> 2500
B8: Discount factor | F8: ='Scenario Engine'!F58 -> 0.95835617 | G8: ='Scenario Engine'!G58 -> 0.8801989 | H8: ='Scenario Engine'!H58 -> 0.80841564 | I8: ='Scenario Engine'!I58 -> 0.74248654 | J8: ='Scenario Engine'!J58 -> 0.6819342 | K8: ='Scenario Engine'!K58 -> 0.6263201 | L8: ='Scenario Engine'!L58 -> 0.57524153 | M8: ='Scenario Engine'!M58 -> 0.52832859 | ... O8: ='Scenario Engine'!O58 -> 0.44566844
B9: PV of A$1/t in that year (A$m) | F9: =F7/1000*(1-Assumptions!$C$31)*F8 -> 0.71445452 | G9: =G7/1000*(1-Assumptions!$C$31)*G8 -> 0.68699524 | H9: =H7/1000*(1-Assumptions!$C$31)*H8 -> 0.6309684 | I9: =I7/1000*(1-Assumptions!$C$31)*I8 -> 0.70944589 | J9: =J7/1000*(1-Assumptions!$C$31)*J8 -> 0.79479431 | K9: =K7/1000*(1-Assumptions!$C$31)*K8 -> 0.90534571 | L9: =L7/1000*(1-Assumptions!$C$31)*L8 -> 0.94627232 | M9: =M7/1000*(1-Assumptions!$C$31)*M8 -> 0.90978184 | ... O9: =O7/1000*(1-Assumptions!$C$31)*O8 -> 0.77991977
B11: Coefficient: A$m of equity value per A$1/t, incl. terminal value | D11: =SUM(F9:O9)+O9*(1+Assumptions!$C$36)/(Assumptions!$C$33-Assumptions!$C$36) -> 20.458192
B13: Lever | C13: Mechanism | D13: A$/t | E13: A$m | F13: A$/sh | G13: Evidence | H13: Source anchor
B14: Sensor-based ore sorting (P680) | C14: TOMRA sorter rejects waste before energy-intensive downstream processing: fewer tonnes milled per tonne of Li2O, so both unit cost and energy per tonne of product fall together | D14: 30 | E14: =D14*$D$11 -> 613.74575 | F14: =E14/Assumptions!$C$12 -> 0.19060427 | G14: Strong | H14: World's largest lithium ore sorter, >1,000t/hr, commissioned Aug-24 in the A$103m P680 project
B15: Power strategy: gas conversion, solar and BESS | C15: Displaces diesel generation at Pilgangoora; company targets ~48% lower power emissions intensity by 2027 and up to 80% by 2030 if regional wind becomes available | D15: 18 | E15: =D15*$D$11 -> 368.24745 | F15: =E15/Assumptions!$C$12 -> 0.11436256 | G15: Moderate | H15: 8 new gas gensets plus LNG storage installed; BESS planned to firm future solar
B16: Mid-stream lithium phosphate (Calix) | C16: Electric calcination cuts calcination emissions by more than 80% and moves PLS one step down the value chain, capturing conversion margin rather than selling raw concentrate | D16: - | E16: see below | F16: - | G16: Moderate | H16: 100%-owned demonstration plant opened 5-Jun-26; first production guided Sep-qtr 2026; ARENA-backed
B17: Social licence protecting the growth option | C17: Heritage and community standing keep P2000 and Colina permittable on schedule; the PFS values the P2000 increment at A$2.6bn NPV, so schedule protection is worth real money | D17: - | E17: see below | F17: - | G17: Moderate | H17: P2000 PFS: A$2.6bn incremental NPV, 55% IRR, first ore guided mid-2029
B18: Low-carbon, non-China supply access | C18: EU Battery Regulation carbon declarations and US FEOC rules favour traceable, low-carbon, non-China units; PLS supplies a Korean JV rather than only Chinese converters | D18: - | E18: see below | F18: - | G18: Weak | H18: No verified carbon-linked price premium in PLS's disclosed contracts - flagged as unproven
B19: Total quantified unit-margin levers | D19: =SUM(D14:D18) -> 48 | E19: =SUM(E14:E18) -> 981.99321 | F19: =SUM(F14:F18) -> 0.30496683
B21: Schedule protection: what social licence is worth on the P2000 option
B22: P2000 incremental NPV (PFS, June 2024) | D22: 2600 | H22: PLS P2000 Pre-Feasibility Study: A$2.6bn incremental NPV, 55% IRR
B23: Permitting / heritage delay avoided (years) | D23: 2 | H23: A two-year slip is the observed order of magnitude for WA heritage and approvals disputes
B24: Value of avoiding that delay (A$m) | D24: =D22*(1-1/(1+Assumptions!$C$33)^D23) -> 406.78548
B25: Per share (A$) | D25: =D24/Assumptions!$C$12 -> 0.12633089
B27: Total shared-value contribution
B28: Unit-margin levers (A$/share) | D28: =F19 -> 0.30496683
B29: Growth-option schedule protection (A$/share) | D29: =D25 -> 0.12633089
B30: Shared value embedded in the target price (A$/share) | D30: =D28+D29 -> 0.43129773
B31: Base-case value per share (A$) | D31: ='Scenario Engine'!$C$72 -> 6.4975772
B32: Shared value as a share of the target price | D32: =D30/D31 -> 0.066378239
B34: THIS IS AN ATTRIBUTION, NOT AN ADDITION.
B35: Nothing on this sheet is added to the DCF. The ore-sorting and power benefits are already inside the
B36: A$569/t FY26 unit cost and the A$575-625/t FY27 guidance that the model discounts, and the P2000 schedule
B37: is already in the production profile. Adding them again would double-count the same cash flow once through
B38: FCFF and once through narrative. What the bridge does is decompose the valuation we have already struck and
B39: ask: how much of it exists because of ESG-linked operating decisions? The answer is A$0.43 per share - which
B40: is 4.6% of the A$6.12 target, but 67% of the A$0.64 of upside between the last close and that target.
B43: Two levers are deliberately carried at nil. The Calix mid-stream plant is real and opened in June 2026, but
B44: first production is only guided for the September 2026 quarter, so we do not capitalise a margin we have not
B45: seen. A carbon-linked price premium is frequently claimed across this sector; we found no verified premium in
B46: PLS's disclosed contracts, so we score it as unproven and value it at zero rather than manufacture a number.

Sheet Downstream Option
B2: The low-carbon downstream option
B3: Sized deliberately OUTSIDE the target price. This is where the shared value actually is.
B4: PLS Group Limited (ASX: PLS) | Valuation date 5 September 2026 | All figures A$ unless stated
B6: Why this sits outside the target. None of the three levers below is earning yet: the mid-stream plant
B7: produces its first lithium phosphate in the September 2026 quarter, the POSCO joint venture is still ramping,
B8: and we found no verified carbon-linked premium in any disclosed PLS contract. We size them here so the reader
B9: can see the prize, and we keep them out of the A$6.12 target so the recommendation does not depend on them.
B11: Lever | C11: Volume | D11: Unit margin | E11: EBITDA A$m | F11: Multiple | G11: NPV A$m | H11: Basis
B12: Mid-stream lithium phosphate | C12: 400 | D12: 480 | E12: =C12*D12/1000 -> 192 | F12: 8 | G12: =E12*F12 -> 1536 | H12: kt of concentrate calcined in-house (20% of a 2Mtpa base), at the conversion margin retained rather than ceded to a third-party converter
B13: POSCO JV equity earnings | C13: 43 | D13: 4200 | E13: =C13*D13/1000*0.18 -> 32.508 | F13: 8 | G13: =E13*F13 -> 260.064 | H13: ktpa lithium hydroxide at Gwangyang, A$/t conversion margin, PLS share 18%. PLS holds an option to lift that stake to 30%.
B14: Low-carbon qualification premium | C14: 1000 | D14: 75 | E14: =C14*D14/1000 -> 75 | F14: 8 | G14: =E14*F14 -> 600 | H14: kt of qualified volume at an A$/t premium. Illustrative only: no verified carbon-linked premium exists in PLS's disclosed contracts today.
B15: Unrisked total | E15: =SUM(E12:E14) -> 299.508 | G15: =SUM(G12:G14) -> 2396.064
B17: Risking and per-share value
B18: Lever | C18: NPV A$m | D18: Probability | E18: Risked A$m | F18: A$/share
B19: Mid-stream lithium phosphate | C19: =G12 -> 1536 | D19: 0.45 | E19: =C19*D19 -> 691.2 | F19: =E19/Assumptions!$C$12 -> 0.21465839 | G19: Plant is built and commissioned; first product due Sep-qtr 2026. Scale-up beyond the demonstration unit is not funded.
B20: POSCO JV equity earnings | C20: =G13 -> 260.064 | D20: 0.7 | E20: =C20*D20 -> 182.0448 | F20: =E20/Assumptions!$C$12 -> 0.056535652 | G20: Both trains built; Train 2 ramping. Lowest execution risk of the three.
B21: Low-carbon qualification premium | C21: =G14 -> 600 | D21: 0.25 | E21: =C21*D21 -> 150 | F21: =E21/Assumptions!$C$12 -> 0.046583851 | G21: Directionally supported by EU and US policy, but unproven in PLS's contracts. Priced sceptically.
B22: Risked downstream option | E22: =SUM(E19:E21) -> 1023.2448 | F22: =SUM(F19:F21) -> 0.31777789
B24: What this does to the recommendation
B25: 12-month target price (A$) | D25: ='Football Field'!$C$16 -> 6.1233073
B26: Last close (A$) | D26: =Assumptions!$C$11 -> 5.48
B27: Upside in the target (A$/share) | D27: =D25-D26 -> 0.64330732
B28: Shared value already inside the target (A$/share) | D28: ='ESG Value Bridge'!$D$30 -> 0.43129773
B29: Share of the upside attributable to shared value | D29: =D28/D27 -> 0.67043809
B30: Plus the downstream option, outside the target (A$/share) | D30: =F22 -> 0.31777789
B31: Target plus the risked option (A$/share) | D31: =D25+F22 -> 6.4410852
B33: The point of this sheet. Measured against the A$6.12 target, the shared-value bridge looks like a rounding
B34: adjustment. Measured against the UPSIDE - the A$0.64 per share between the last close and the target - it is
B35: most of the investment case. The market is paying for a lithium miner. We are paying for the operator whose
B36: carbon position and downstream reach let it sell tonnes the others cannot. That gap is the recommendation.

Sheet Returns
B2: Returns
B3: Against the fund's benchmark and mandate
B4: PLS Group Limited (ASX: PLS) | Valuation date 5 September 2026 | All figures A$ unless stated
B6: Mandate
B7: S&P/ASX 200 return, FY26 | C7: =Assumptions!$C$58 -> 0.059 | D7: Case p.4
B8: Fund return, FY25 | C8: 0.079 | D8: Case p.4 - beat the index by 2.0%
B9: Outperformance the fund must repeat | C9: 0.02
B11: This recommendation
B12: Entry price (A$) | C12: =Assumptions!$C$11 -> 5.48
B13: 12-month target (A$) | C13: ='Football Field'!$C$16 -> 6.1233073
B14: Capital return | C14: ='Football Field'!$C$18 -> 0.11739185
B15: Dividend yield, FY27E | C15: ='Income Statement'!F25 -> 0.016698836
B16: Total shareholder return, 12 months | C16: ='Football Field'!$C$20 -> 0.13409068
B17: Excess return over benchmark | C17: =C16-C7 -> 0.075090683
B19: Multi-year hold
B20: Bear case value per share (A$) | C20: ='Scenario Engine'!$C$37 -> 2.2647124
B21: Base case value per share (A$) | C21: ='Scenario Engine'!$C$72 -> 6.4975772
B22: Bull case value per share (A$) | C22: ='Scenario Engine'!$C$107 -> 8.9343473
B23: Downside to bear | C23: =C20/Assumptions!$C$11-1 -> -0.58673131
B24: Upside to bull | C24: =C22/Assumptions!$C$11-1 -> 0.63035535
B25: Reward-to-risk ratio | C25: =IFERROR(ABS(C24/C23),0) -> 1.074351 | D25: Upside to bull divided by downside to bear
B27: Stress test: does the bear case clear the price the market actually printed?
B28: 52-week low, actually traded (A$) | C28: 1.91 | D28: Reached when spodumene was at its trough
B29: Our bear case (A$) | C29: =C20 -> 2.2647124
B30: Bear case premium to the traded low | C30: =C29/C28-1 -> 0.18571332
B32: At the A$1.91 low the company held A$974m of cash and was loss-making. It now holds A$2,290m and earned
B33: A$526m. Our bear case assumes prices revert to the marginal cost, P2000 is never sanctioned, Colina never
B34: proceeds and volumes stay flat for a decade - all at once. Reaching the old low from here would take
B35: conditions materially worse than the trough the market has already lived through.
B37: A long-only fund benchmarked to the ASX 200 needs positions where the asymmetry, not just the point estimate, is favourable.

Sheet Sources
B2: Source register
B3: Provenance for every input. Tags: A actual, G guidance, M market, D derived, E our estimate, C prescribed by the case
B4: PLS Group Limited (ASX: PLS) | Valuation date 5 September 2026 | All figures A$ unless stated
B6: Input | C6: Value | D6: Tag | E6: Source
B7: Risk-free rate | C7: 5.00% | D7: C | E7: FMAA / Shared Value Project, Investing for the Future Case 2026, p.6 - prescribed
B8: Market risk premium | C8: 6.00% | D8: C | E8: FMAA case p.6 - prescribed
B9: Equity beta | C9: 0.73 | D9: C | E9: FMAA case p.6, sourced there to Yahoo Finance 5Y monthly
B10: Benchmark return FY26 | C10: 5.90% | D10: C | E10: FMAA case p.4, S&P/ASX 200
B11: Last close | C11: A$5.48 | D11: M | E11: Market Index and Google Finance quote pages, early Sep-2026
B12: 52-week range | C12: A$1.91 - A$6.81 | D12: M | E12: Market Index, ASX:PLS
B13: Shares on issue | C13: 3,220m | D13: M | E13: stockanalysis.com; consistent with ASX quotation notices (~3,223.6m)
B14: FY26 revenue | C14: A$1,934m | D14: A | E14: FY26 results, 24-Aug-2026; +152% YoY
B15: FY26 underlying EBITDA | C15: A$1,137m | D15: A | E15: FY26 results; 59% margin
B16: FY26 statutory NPAT | C16: A$526m | D16: A | E16: FY26 results
B17: FY26 production | C17: 879.5kt | D17: A | E17: FY26 results; +17%, beat guidance by ~10kt
... B54: Huayou / Atlantic Lithium | C54: US$210m at a 26.6% premium, announced May-2026 | D54: M | E54: Company announcements
B56: Verification note. Company sites and the ASX announcements platform could not be opened directly from the
B57: environment used to build this model, so reported figures were corroborated across two or more independent
B58: secondary reports of the same announcement rather than read off the primary PDF. Headline FY26 figures are
B59: consistent across sources. Figures tagged E are our own estimates and are identified as such wherever they appear.
B60: Known unresolved items: total borrowings at 30-Jun-26 (only the US$600m notes issue is confirmed); FY24
B61: comparatives; the Ore Reserve has not been restated since August 2023; and PLS's Scope 3 emissions are not disclosed.
